[{"run_id": 9223370501615189093, "name": "Run from keep", "distance": 3237.7822, "moving_time": "0:22:35", "type": "Run", "start_date": "2018-08-25 23:03:43", "start_date_local": "2018-08-26 07:03:43", "location_country": "{'latitude': 29.302595757378473, 'longitude': 120.07077365451389, 'country': '\u4e2d\u56fd', 'nationCode': '156', 'province': '\u6d59\u6c5f\u7701', 'city': '\u91d1\u534e\u5e02', 'cityCode': '0579', 'district': None, 'districtCode': None}", "summary_polyline": "chyqDwny{UERCP?JFfAHJDPFLBP@La@n@ORyh@o@JKEEKAKDM@Q?g@Qg@?MEEaAQ{@G_AQiAQm@KMi@w@UYMKGOGa@EOKUKMeAOo@EQCu@Oc@IOAKBEHEHCZCNAPQXENCbA?dAHdAFhAD|@JX@d@Hb@@T?VBPJHFR|@PTCTERENC|@a@LGp@?|@Et@MJCX@JWE_A?MDKDe@ECBOGq@?M@IAQIi@GSEQAe@]_@g@e@]]WKa@o@_@YSGWC?NKFM?{@Qg@BKBW?SFKJOZENKH?PIR?VGb@Ar@DnA?`@DLANIn@@TTnA\\t@HPFd@HLXAJ?RSLI\\Ov@DN?\\Rr@GVSXIJINGv@?ZLL@LAFGCWCOAQAe@Ee@EM?KPELLN\\", "average_heartrate": null, "average_speed": 2.3895071586715866, "streak": 1}, {"run_id": 9223370501443329092, "name": "Run from keep", "distance": 3023.9465, "moving_time": "0:22:59", "type": "Run", "start_date": "2018-08-27 22:47:44", "start_date_local": "2018-08-28 06:47:44", "location_country": "{'latitude': 29.299922417534724, 'longitude': 120.0703209092882, 'country': '\u4e2d\u56fd', 'nationCode': '156', 'province': '\u6d59\u6c5f\u7701', 'city': '\u91d1\u534e\u5e02', 'cityCode': '0579', 'district': None, 'districtCode': None}", "summary_polyline": "ojyqDqpy{UXr@Vl@HNVx@Tj@Nv@?TIRMJ[?UCOKMA_@D[CcAH{@Cq@@o@J}@HYB]Bu@Kq@M}@K}@?c@Aw@Kc@K]Eg@i@MGGKOm@GMQWWm@GK?O?QASEQIIICGEIKCKEKg@g@[]Sc@Oq@GQMQIOOa@ScAESGCH?M_AU_AIKUs@BOAOYcA]s@Oa@c@s@Wk@SYS{@Uq@[g@]YEECKOa@SUi@MWK[BIDi@QYIK@_@`AGn@UhAS`AQdAOfAMbAAd@Or@@PShAWjA?RDNHJp@Rv@RNB^AJBZVLHTBNAh@DJRJEPJPXNJLD`@@`@QLOl@g@NKRIl@Sx@[`@MLGTEFKEJDHBJ@JJTHBJIPGFAL@NFPRA\\AZFLLf@^t@X|@R~@FJFDBJDHLRFLFNB^AHKt@Ft@Lh@@JDH^E", "average_heartrate": null, "average_speed": 2.192854604786077, "streak": 1}, {"run_id": 9223370501097422599, "name": "Run from keep", "distance": 2179.824, "moving_time": "0:12:52", "type": "Run", "start_date": "2018-08-31 23:02:57", "start_date_local": "2018-09-01 07:02:57", "location_country": "{'latitude': 29.303906792534722, 'longitude': 120.0772878689236, 'country': '\u4e2d\u56fd', 'nationCode': '156', 'province': '\u6d59\u6c5f\u7701', 'city': '\u91d1\u534e\u5e02', 'cityCode': '0579', 'district': None, 'districtCode': None}", "summary_polyline": "qkyqD_ry{Ue@[`@bADLNVx@`BDPBROj@IP?VMLGN]bAo@P[AYCWASAm@@O?}@?cASs@O{@Mc@EeAFQFYEa@OQMk@Y{@QYOKAIEGUDQOi@CWM}@S}@Se@MAQN[AKCKM_@m@a@w@Sa@Go@OkAK]Uk@CRMc@IKKKi@r@SVk@\\QDs@d@{@`@QDSAu@a@QKSI}@Sq@MYD]G_AYw@Sa@SKKIWHSDODODODMBoAFw@BQCk@?_@Hq@`@cAHM^gA@QLa@H}@RaAHQJKb@ATKFH", "average_heartrate": null, "average_speed": 2.8236062176165806, "streak": 1}, {"run_id": 9223370500751668670, "name": "Run from keep", "distance": 3081.0774, "moving_time": "0:25:47", "type": "Run", "start_date": "2018-09-04 22:52:36", "start_date_local": "2018-09-05 06:52:36", "location_country": "{'latitude': 29.30472900390625, 'longitude': 120.07649197048612, 'country': '\u4e2d\u56fd', 'nationCode': '156', 'province': '\u6d59\u6c5f\u7701', 'city': '\u91d1\u534e\u5e02', 'cityCode': '0579', 'district': None, 'districtCode': None}", "summary_polyline": "_vzqDiyy{Uw@Z]HOB[Ii@c@MMMMOIo@UIGMBw@Oq@OYO@Ei@c@H@b@HrLvBBMe@n@IFa@N[PSBMCKIIGMCk@a@MO]Oc@i@KGY@s@YaAMm@AWMGWHeAP{@FWb@_AFSBS?cA?MJaAX_A\\{@Zs@H_AHk@Pa@FIZKJDh@^LFLDNDJNt@b@ZPd@?b@x@HN@RDHHf@h@j@@PBj@BTDTDNh@l@HNFTBPAd@?RFR`@d@@LBZBPDd@DJAJs@b@SNIJ}@Rg@JKJc@Rm@^c@JUKq@o@g@m@SK_AQ_@M_AOu@Qg@QIKHe@NiA@y@Ty@HYJi@Dm@HYLcAJo@", "average_heartrate": null, "average_speed": 1.9916466709760827, "streak": 1}, {"run_id": 9223370499024056539, "name": "Run from keep", "distance": 2778.993, "moving_time": "0:18:26", "type": "Run", "start_date": "2018-09-24 22:53:30", "start_date_local": "2018-09-25 06:53:30", "location_country": "{'latitude': 29.30152072482639, 'longitude': 120.07294135199653, 'country': '\u4e2d\u56fd', 'nationCode': '156', 'province': '\u6d59\u6c5f\u7701', 'city': '\u91d1\u534e\u5e02', 'cityCode': '0579', 'district': None, 'districtCode': None}", "summary_polyline": "mpzqDc|y{Uo@ZkA^w@b@ULUFGFI?q@Yg@YeAe@{@WaAQcAOk@IQMEO@_@LiAHcAPaAN{@PaARoAPiAVeAXkARu@HIr@I^@j@ZLPt@f@p@j@l@r@h@x@b@|@^fAT`AFXZ~@XlAVx@Vz@@N[`@o@f@{@`@MD]D}@\\s@^QFO@u@]q@g@g@]aAYs@G{@Sc@Ga@MCy@JsANiANeAJaAL_AT}@RiAT}@X{@T_ADKFGNAl@R@JRPhAZh@Nf@Zf@t@Vj@HJ\\t@Vx@Zt@Vn@TbAZz@XfAT`AF`@HBDII@BLT^Lz@?N", "average_heartrate": null, "average_speed": 2.5126518987341773, "streak": 1}, {"run_id": 9223370498850055600, "name": "Run from keep", "distance": 2702.4475, "moving_time": "0:16:36", "type": "Run", "start_date": "2018-09-26 23:15:21", "start_date_local": "2018-09-27 07:15:21", "location_country": "{'latitude': 29.30151312934028, 'longitude': 120.07293484157987, 'country': '\u4e2d\u56fd', 'nationCode': '156', 'province': '\u6d59\u6c5f\u7701', 'city': '\u91d1\u534e\u5e02', 'cityCode': '0579', 'district': None, 'districtCode': None}", "summary_polyline": "}rzqDszy{Uy@Zi@RWNkA\\MCq@m@UU_Ac@w@WcASa@KQGa@EIICK@_AFmAJ}@RmAH}@BKDKN_AR}@Py@RgAReAXk@b@CZTd@NVFv@Z`@NNHd@z@P\\\\\\b@fARt@Zv@Zv@ZdA\\~@\\dAJ^BPALg@t@q@h@s@\\k@PUN[HaAd@]JIGKOOIg@_@m@[{@]{@O_A[aAMKMCKFuAL{@FaANkAReATeARkATgAXiAZ}@FMRKTBRC`@Pj@\\v@Ph@h@h@v@^r@Zt@\\r@Xv@V~@Z|@X~@Xz@XbADJ?N?HR|@BFZPPBFHEJ?N", "average_heartrate": null, "average_speed": 2.713300702811245, "streak": 1}, {"run_id": 9223370498591377547, "name": "Run from keep", "distance": 2705.1199, "moving_time": "0:15:14", "type": "Run", "start_date": "2018-09-29 23:08:00", "start_date_local": "2018-09-30 07:08:00", "location_country": "{'latitude': 29.301754828559027, 'longitude': 120.07375759548611, 'country': '\u4e2d\u56fd', 'nationCode': '156', 'province': '\u6d59\u6c5f\u7701', 'city': '\u91d1\u534e\u5e02', 'cityCode': '0579', 'district': None, 'districtCode': None}", "summary_polyline": "qqzqDqzy{UKDm@I[Lq@b@s@`@SCS@QCOEq@a@q@a@IKaA_@g@KUAy@Og@GGGCIAoAJqAF_APkANcAPgATiAX{@NaAPw@Pg@FGp@Ap@Tr@\\p@ZZ`@j@f@f@v@LX^fA`@lAR~@Tx@NZFFNb@FHJ\\Np@D|@CRKF_@j@o@d@y@Zy@Z_AVYRQCUKWUk@c@u@c@w@Sw@K{@Sy@UGi@@iA@MLgAPgAN{@NeAHy@XqAP}@Je@FQHm@P]TKf@GLHTD^PJLd@Lz@`@Z\\b@v@^x@Zv@Z|@Z|@Rb@Rz@Tx@X|@Jb@JRD\\IXSb@FEV[", "average_heartrate": null, "average_speed": 2.9596497811816196, "streak": 1}, {"run_id": 9223370498245333333, "name": "Run from keep", "distance": 3852.6091, "moving_time": "0:26:17", "type": "Run", "start_date": "2018-10-03 23:04:33", "start_date_local": "2018-10-04 07:04:33", "location_country": "{'latitude': 29.301988389756943, 'longitude': 120.07459988064237, 'country': '\u4e2d\u56fd', 'nationCode': '156', 'province': '\u6d59\u6c5f\u7701', 'city': '\u91d1\u534e\u5e02', 'cityCode': '0579', 'district': None, 'districtCode': None}", "summary_polyline": "_rzqDqzy{Uk@Ta@L{@V[H_@PWE}@i@w@c@w@g@o@Mi@AaASc@IMKEK?[De@D_ATsAFs@L_AD[PaANaATs@TiAR_APq@HMLEJAr@VTHv@f@x@TVNb@p@^p@\\t@Vl@P|@X`AH^H\\`@v@Lf@HNBNXz@J`@ALWl@o@n@EJ_@RYFI?OEI@YRgA^g@VU@[Si@i@m@]w@U_AM]Ou@Kq@QGKFwA@i@LgALcAPiATaAPkAR{@R{@P_AXu@BIJILEZBx@Vn@ZPDJJRH\\Tf@n@`@~@Td@Vl@^t@Xx@F^Tn@Np@Zv@VfADVIh@g@~@U`@IJ}@V_ATUFs@\\QD[?OEe@m@c@]s@Wi@Qw@M_@Ky@Ia@KMICOA_@BON}@H_AH_@DkABY?]DS@IJKNa@P_AN{@TmAPy@Rw@NM~@Dv@\\z@\\b@RVVb@l@Zd@Xx@`@x@Xh@DV?VHJNl@FNZZDJHTH@", "average_heartrate": null, "average_speed": 2.442998795180723, "streak": 1}, {"run_id": 9223370498158279038, "name": "Run from keep", "distance": 3519.0435, "moving_time": "0:22:41", "type": "Run", "start_date": "2018-10-04 23:18:52", "start_date_local": "2018-10-05 07:18:52", "location_country": "{'latitude': 29.303837348090276, 'longitude': 120.07726616753472, 'country': '\u4e2d\u56fd', 'nationCode': '156', 'province': '\u6d59\u6c5f\u7701', 'city': '\u91d1\u534e\u5e02', 'cityCode': '0579', 'district': None, 'districtCode': None}", "summary_polyline": "uqzqDi{y{UKHQHm@Dm@`@y@j@[JK?w@k@{@m@s@[KAy@Qu@OcAO_@COSJoAR{@H_AHcAL}@RmANcATgAT}@BSHKNs@HKN]j@C`@Jl@b@`@Hb@Pd@`@f@j@PZHF`@v@Zz@V~@HVXr@X~@R~@Vv@Z|@Dd@ITONOd@]h@YTu@Ru@A]@]LURMDSEq@]o@a@o@YcAUw@Oi@K_AOSKGIEWJc@?OPkAJcAPkAJcAHQNaATcAFYXeAVaAXk@HMLGXBVNbA^~@ZVPl@l@NPd@|@LXV|@Xz@h@~@BRDJJn@TfAZbARj@Dd@e@l@u@t@YT]B}@NMD{@`@_@JSEu@e@s@_@a@[{@S_ASi@Mw@GMCKQE]Bg@Hg@JiAHq@Lk@PgAJs@Hu@Ne@NcATy@Ty@L_@DSFILIt@@X@", "average_heartrate": null, "average_speed": 2.5856307861866275, "streak": 2}, {"run_id": 9223370497900668247, "name": "Run from keep", "distance": 4094.015, "moving_time": "0:26:38", "type": "Run", "start_date": "2018-10-07 22:48:26", "start_date_local": "2018-10-08 06:48:26", "location_country": "{'latitude': 29.30231391059028, 'longitude': 120.07318522135417, 'country': '\u4e2d\u56fd', 'nationCode': '156', 'province': '\u6d59\u6c5f\u7701', 'city': '\u91d1\u534e\u5e02', 'cityCode': '0579', 'district': None, 'districtCode': None}", "summary_polyline": "opzqDg{y{UUXUJ{@LeAZu@Xk@BKCy@i@y@k@s@Ym@QQKu@Iw@KQGEICiAFgABk@TmALkARaAFi@T{@Js@XaATaABSP_@JINEJPRPz@TbAZx@f@JH^f@f@`Ab@~@Rj@TbAZdAL^Jf@Z|@X~@?NF`@Af@GTWXy@\\q@H]Hs@^{@\\]DK?q@_@k@a@s@]i@SaAM{@KMAOGICQSE{@D_AF_ANcANkAPeAL_AXcARs@B]ZiAPWDMNMr@Br@Xv@X^Hj@f@f@r@f@x@LT^bAZ~@\\bATb@L~@Rx@Pp@?PHPHh@ITe@l@Ud@q@f@y@HIDi@FoA`@WBy@q@[[e@YeAU}@M{@Ui@KIEIMEM?[Ba@DOJ{@D}@@QJe@BWFMJy@DORwAP}@R}@Rs@BQXc@Vi@FGf@DZXj@X~@Vv@d@f@j@h@~@Xv@T`AXt@R^ZfARz@Rn@NVTv@Y`A]`@CJKPIDKRg@JSCJM", "average_heartrate": null, "average_speed": 2.561961827284105, "streak": 1}, {"run_id": 9223370497640188353, "name": "Run from keep", "distance": 5040.7627, "moving_time": "0:37:53", "type": "Run", "start_date": "2018-10-10 22:58:30", "start_date_local": "2018-10-11 06:58:30", "location_country": "{'latitude': 29.304441731770833, 'longitude': 120.07744466145833, 'country': '\u4e2d\u56fd', 'nationCode': '156', 'province': '\u6d59\u6c5f\u7701', 'city': '\u91d1\u534e\u5e02', 'cityCode': '0579', 'district': None, 'districtCode': None}", "summary_polyline": "srzqDkzy{U}@TMDSDs@Xc@POBw@i@m@_@{@_@s@YcAOeAQ_@OEK?q@NeANaAN_AL_AR}@DUDeA?SJUFm@b@kALw@HYR]HGVCFLbAZb@NVFV@n@x@h@r@f@n@d@`AVbA@PZx@Xz@FL@TTbA^dAVx@?Rk@t@i@j@i@^K?aARu@Vq@RU@QCu@g@m@a@}@]YIk@GaA[_AMIMAMDUFuAJ}@LcAPsAPy@J_AXkANcAT{@Nm@Re@LGb@J|@`@t@Pl@Vj@d@VZb@v@`@n@DHBZRh@DVDF?LXv@Tx@Tv@Nn@^z@Rt@?NSd@e@`@EHg@\\SRWDWHWBy@Xk@XM@w@]m@c@q@Ys@S{@S_@COIu@K]MKMCONgAFQBi@LkALkARiANiARaATaARaARs@P_@FGb@Ct@LRD^Vr@X`@Zh@x@V\\JHXZ\\n@F`@JVTjAH^LVPp@Vx@`@~@Lv@?VDLL@IJk@X]r@Y\\GBKCHKb@DL?HGFMVSTs@@KI?EJa@NKHGl@ENY@GJCHGFUFg@BMCUDW?IBq@d@g@XMAMIGKMGIKg@WM@ICAKMOKCIGI?GCWAGKg@CMAU@SOCKo@a@I?KIQk@@OAOBMC]Rk@CYFQ?OFKDi@Ci@FKF[CMHW?KHEDK?KDKEOBIJM?OLW?OBWRe@JQFOF_@AM@KFG@[DM", "average_heartrate": null, "average_speed": 2.2176694676638804, "streak": 1}, {"run_id": 9223370497553369010, "name": "Run from keep", "distance": 5319.1143, "moving_time": "0:33:16", "type": "Run", "start_date": "2018-10-11 23:10:15", "start_date_local": "2018-10-12 07:10:15", "location_country": "{'latitude': 29.30169759114583, 'longitude': 120.07356309678819, 'country': '\u4e2d\u56fd', 'nationCode': '156', 'province': '\u6d59\u6c5f\u7701', 'city': '\u91d1\u534e\u5e02', 'cityCode': '0579', 'district': None, 'districtCode': None}", "summary_polyline": "eqzqD_{y{UQ?k@Dw@`@q@b@m@ZSD}@_@]W[[s@[_AWe@GIEu@Km@EOKEMDgALgAFo@RaANgAJ_AJcAR_AJa@BUPi@R}@J_@JONMXB~@b@|@N`@Pr@r@h@l@V\\Tn@PR^hA^~@FLTnAZz@FNZ~@BLLN@LO`AELANOj@QTW@o@BcAR_@NKHq@RULWAcAk@s@a@UOy@[q@IKGw@Kw@OGW@{@J_AJoAL}@Lm@N_ANgANeAXcAReAb@eALQHA|@Vp@^H?LJh@N`@VVZFNf@f@h@|@NZVfAV|@ZlATl@Vz@\\bAHRDREd@i@~@i@t@OJc@Aa@B{@Ts@TYLUAq@e@o@c@{@[aAQs@Su@QYEWMEG@o@NaAHaAJ}@LaAP_APiATeAVkAPaA\\y@TSXIXJv@j@x@Xp@^p@l@b@v@^`AZz@X`AP\\Rx@FPLXZfATx@Lp@@PGl@GLaAp@u@TMCeAV}@Z[NMBMCm@a@g@]ME_@Wu@Uu@Oa@E_@Ku@KQQEGDgAJkANgAJk@JiAZsAF[L{@VsAXeANi@Pc@LEr@JXNPR\\HL@d@Np@d@\\`@PHj@p@Xj@BL@LZ|@Rz@J`A\\fA`@|@^jAJ\\", "average_heartrate": null, "average_speed": 2.6648869238476953, "streak": 2}, {"run_id": 9223370479214634718, "name": "Run from keep", "distance": 6792.208, "moving_time": "1:08:12", "type": "Run", "start_date": "2019-05-04 18:46:41", "start_date_local": "2019-05-04 20:46:41", "location_country": "{'latitude': 52.27492011018211, 'longitude': 10.522813768522198, 'country': '\u5fb7\u56fd', 'nationCode': '276', 'province': None, 'city': None, 'cityCode': None, 'district': None, 'districtCode': None}", "summary_polyline": "{ra~Hyre_As@^MGWAo@Js@l@YTy@d@MNWL_ATu@h@q@p@g@R{@LIJa@N{@AcAUy@WSCe@WMKaA[y@U{@Iu@Ie@McA@eA?{@?}@DaAB_@BaAQy@C_A?cA@q@Lu@@}@B}@B[F_ABeALu@@UFu@D{@TaA`@w@b@_@DUHe@B[FHII?JJRCc@HM?IFG|ABp@Ih@AVIpABx@HVHh@FrBFhBBxAJdB@T?zA@PDPD`ABxABdBPtAHhBBRAh@H`BCR@z@@NXOVCf@SL@`AIx@@l@Ab@PRKh@@?~AIv@GPCXBnABh@CdAETGJMzA?b@WbB_@xASfAUb@SPYLc@d@g@bAKNMb@Id@A|@Df@\\jA^n@ZVh@^RXHXJJZCZYf@WHAPX\\xAPv@DJHXjAjBZTv@T^Dn@aAf@aAV_ALUBg@BOL]RiACOFGBQ@c@\\{AF]D_@Pq@BSDS@m@EaBAc@I_@AUMu@AiBDqACQ@e@AiBBk@^mAJa@Ba@@kBCmBAS@e@MeBS}A]qA]{A_@cBYaBKo@BMTBLAfAHx@C~@A`@Dv@Ex@@|@@bA@j@Bt@If@AHB^Ev@F|@Az@E`AD|@@x@Db@PZb@JLn@Sd@]bAMx@Cn@@JDTIJINIL@x@AHCN@h@Td@DNAJFdAAt@?x@C|@IdAJ|@GHEHDHUn@IYJWCKEEKHCFJH@JIARJOT@FMXLLBHE|@?h@ALIDQCSMaB?g@LwADo@GkAa@qAUiA?YG_ADgBB{APgA?SXeB\\cAf@iAP_@ZmAHe@A{@CUBgAAu@BMTUHCRUNs@?_BE_A@OCuAE_@", "average_heartrate": null, "average_speed": 1.6598748778103616, "streak": 1}, {"run_id": 9223370478826030933, "name": "Run from keep", "distance": 5009.3594, "moving_time": "0:38:36", "type": "Run", "start_date": "2019-05-15 18:27:16", "start_date_local": "2019-05-15 20:27:16", "location_country": "{'latitude': 52.278545863099524, 'longitude': 10.541239103014046, 'country': '\u5fb7\u56fd', 'nationCode': '276', 'province': None, 'city': None, 'cityCode': None, 'district': None, 'districtCode': None}", "summary_polyline": "_ra~Hgqj_A_AYE\\KH}@TYNS\\YA]SMHERJvAd@jBPnAJtAJ`AFNHBVCPDR`@P|AB\\Nd@HFv@Y|@_@JEHSBUGcAScBScB?QVSd@}@F[Aw@UaBESQ_@i@Y]G{@Fy@Tw@VUP{@FGJ@n@DN@Tb@tAJv@HdB@VTpAHRh@MJ?Lb@LtAHl@DXHDr@I|@_@XSFMDSOoBSgBImAf@s@J[DYB_@SmBKk@O[k@U_AAcARaATYPo@?MV?`@@VZzATvAN|APbBLb@r@YHNNfBRpAPXJAz@i@t@YLGJIBUO_BQ}AMyAES@O\\QLOTk@DS?SUsAUcA_@s@MEy@E}@Fs@Lm@PWNk@@KJAhAN|AP~@Pp@LhBHhAFVJDd@OL?FJ?RR~AHl@L\\LDPMTYz@YZGJGFQKaBOcBGsAKa@BQFKHBROVa@DSBYGaAWmAg@u@YQi@@eAReAFOD[Tw@HO\\JdBTtALl@LxA@NFTR~AJFt@a@LPDRLvALnATD\\Gr@]f@QJMBQGgBSyAESEm@ES@_@b@_@N_@Hy@EgASuAa@m@MI}@AaAJcAPe@Zo@BWLEP?XXrAZxAPrAFlBDn@FTv@ULUKFDHFXPzA", "average_heartrate": null, "average_speed": 2.1629358376511227, "streak": 1}, {"run_id": 9223370477960571814, "name": "Run from keep", "distance": 3793.6248, "moving_time": "0:34:50", "type": "Run", "start_date": "2019-05-19 17:31:36", "start_date_local": "2019-05-19 19:31:36", "location_country": "{'latitude': 52.279196213014636, 'longitude': 10.544612025978832, 'country': '\u5fb7\u56fd', 'nationCode': '276', 'province': None, 'city': None, 'cityCode': None, 'district': None, 'districtCode': None}", "summary_polyline": "_ya~Hcij_AXvAPzALfAFTTLJGJ?HNVrAVx@RXRCJDx@QH@TSFUAuAS_BEWEu@G]@Ob@k@Ro@Fk@Cw@SkACWGW]Yw@S]A_APaAXIBEHaAHUZATV|@NpAL`@Pz@@X?f@Fx@Jx@DRp@ST?QEJTJzABVLt@DJLFt@Qv@WNKPWAaBQuAISAWBYAQIW?STWb@_AHq@Ao@UuAUq@KQu@Eu@AcARw@PSNOD[EMJGP@d@K`@TdAXr@?ZPbANfBFz@PHVIJ?FFVv@V~AHd@JFH@x@a@d@QPQFU?_BU}ACO?m@I[AWDOh@i@La@DYMcAMyAI_@UWu@SIEy@J{@Po@NKNe@@SCUPAVF`Ab@xADZANFXNhBL|A@Lh@B\\ATbBLpADJLLPBz@Ot@WVSFOKwAU}AKg@MoA?QNCLUL_@Jw@GkBGi@Oe@u@q@o@EGBg@GWFMAIDEJg@PU?U^LdBFfA?NJnAZf@HDBz@Jf@A\\BLLWAO?oAEQOBY}@GKOeA@_@G_@BO", "average_heartrate": null, "average_speed": 1.8151314832535885, "streak": 1}, {"run_id": 9223370477958870901, "name": "Run from keep", "distance": 4000.4087, "moving_time": "0:28:19", "type": "Run", "start_date": "2019-05-26 18:10:19", "start_date_local": "2019-05-26 20:10:19", "location_country": "{'latitude': 52.27876805547978, 'longitude': 10.542444037662174, 'country': '\u5fb7\u56fd', 'nationCode': '276', 'province': None, 'city': None, 'cityCode': None, 'district': None, 'districtCode': None}", "summary_polyline": "wsa~Hmzi_AFLJFRG\\Y|@_@NODKB[Am@SeBQ}AKg@FQ^s@Nk@@o@IeBGg@g@g@u@Gm@?eAN[BY\\MF[BUFQ`@CTBf@VtAJ\\V`BLrAJn@FRH@^XH@\\~ALt@HPRR|@i@n@]VYMqBSaBCo@EW?[DK^_@L]DW@e@UgBW}@]]q@C}@H{@T_@L[LIEODQAWL?TPjBVrAPnABp@NvA@PDLZBZIHVV|AHv@Ld@j@In@a@n@UHK?QAQ?OImBOuAIs@EOn@{@Lg@BYMiBMgAY]OK{@Ge@Au@Vy@TKDONg@EKHEPCz@V~AXpAJhA@`@NvAFZT@VILNXbBNz@NZLFp@[x@_@PQB]?w@OuAMqA?QGk@l@mANa@CkAUiBKY_@]]QcAFy@Pm@Ni@T[?WFKJEN@z@DRFNPfAV`APdBJrAFZHLf@MLRFRTdBHh@HTLFH@`@Sl@SHOh@[?aAMqAQuAEUAc@ES@Q`@c@\\}@@OAu@WcBIa@KQe@OaA@w@Ls@JSH]Xi@JILQAILANFn@Hb@Fl@ZlATxARxAFd@`@ML?FDRn@@T", "average_heartrate": null, "average_speed": 2.3545666274278987, "streak": 1}, {"run_id": 9223370477698040493, "name": "Run from keep", "distance": 5042.1904, "moving_time": "0:35:30", "type": "Run", "start_date": "2019-05-29 18:30:01", "start_date_local": "2019-05-29 20:30:01", "location_country": "{'latitude': 52.277961294666014, 'longitude': 10.543212246768967, 'country': '\u5fb7\u56fd', 'nationCode': '276', 'province': None, 'city': None, 'cityCode': None, 'district': None, 'districtCode': None}", "summary_polyline": "qpa~Hs{i_Aj@OHQ@USeBSwAOcBj@w@Pg@BW?q@MsAEUISa@g@_@Es@FcAPs@NYVw@GOJGT@f@Lz@^vARjBNvAB`ARHf@KHHJzALx@DTTZj@WRENK\\I\\SBU@o@M_BQyAGsAFKFCZ_@JYJu@?YScAU}@SKS_@_@KgAL}@PaAPIF[EMDMb@C`@Bl@H^\\hAHb@C|AJrANn@LLv@SL^PzAHTJn@HLJ?z@]z@c@HO@UKwAMoBCi@Ms@HOZ_@Vs@B[AeAS}AQ[a@Wy@Is@H]@gAZc@L]?OBGJCZAb@@\\Nl@Vp@ZdBAVF|@Bl@H\\AZj@CLEJJVrA@v@HTBPDHLDp@CTYLEPU^IFMG}AUoBE_ACUGKDSh@i@HOJi@FuACUYoAk@k@]Km@Fa@Cu@Ps@Rs@`@]EGDE\\?`@Z~AVbBT~AFf@?j@@NLLj@CLFXdBRpAFJZCx@YXGXOLKDWK}@KuAOkBMk@TUXo@Jo@BYKkAAu@G_@KOe@c@MC_ATi@N{@F[Fc@Pe@CGLK`@Ez@Jz@Xf@Pz@BvAPvALv@\\ORELBVbBDd@Jf@HVJHx@[x@]JIJS?w@SaBKaBEk@?STa@PSRs@BSGiBKm@M]k@g@_@C_AF{@Pm@La@Xu@?SNAf@Fr@Z|AX~AFdBLnAJPH@RMRCTr@RvANn@LP~@Y|@e@Tk@DUA_AEYAWCM?UK}@@_@MB", "average_heartrate": null, "average_speed": 2.3672255399061033, "streak": 1}, {"run_id": 9223370467836858959, "name": "Run from keep", "distance": 3546.3044, "moving_time": "0:26:05", "type": "Run", "start_date": "2019-09-20 21:50:55", "start_date_local": "2019-09-21 05:50:55", "location_country": "{'latitude': 29.299522840711806, 'longitude': 120.09970865885417, 'country': '\u4e2d\u56fd', 'nationCode': '156', 'province': '\u6d59\u6c5f\u7701', 'city': '\u91d1\u534e\u5e02', 'cityCode': '0579', 'district': None, 'districtCode': None}", "summary_polyline": "_|yqDgs~{U_AFk@?_ACa@DYVEV?PPx@RZ`@Fz@Bv@@p@CXORWBM@YOa@MQMKWKy@CaA@]@YLUXIPBz@HRRNPD|@@z@Ex@?XILWHi@Ke@U[SKcAE}@Dg@@YHY^GJCPD`@DNHLZNz@@l@Cx@?h@OTQH[A_@EOWWSKg@KgA?q@BKAUBa@XGr@@PNb@NJZFdA?v@@`@GL?LEPOHQHa@E_@EOSQu@IaAE]@]DKCYJ[XIRETB`@DJ^Vb@Hz@?dAAd@ETKPQFO@_@G[UYi@OOA]DGEkACa@BODSVGn@@`@LVNNNDdA@t@Cl@A^QLML_@@OG[QW[Qu@Gg@Aw@@]Dq@^EVAXHZPXPPdABv@Ar@ALCRIVa@Bg@Oe@SSaAK_AH}@FUJGJO|@?XBJRN\\Fx@B^@d@Kv@GJEVWLk@DGHEVmABKC_AB}@Di@GO_@c@[e@k@YO]E_@BUAKQYICo@?WD", "average_heartrate": null, "average_speed": 2.266009201277955, "streak": 1}, {"run_id": 9223370467355882980, "name": "Run from keep", "distance": 3489.2173, "moving_time": "0:23:21", "type": "Run", "start_date": "2019-09-26 11:31:28", "start_date_local": "2019-09-26 19:31:28", "location_country": "{'latitude': 29.299720865885416, 'longitude': 120.09679361979167, 'country': '\u4e2d\u56fd', 'nationCode': '156', 'province': '\u6d59\u6c5f\u7701', 'city': '\u91d1\u534e\u5e02', 'cityCode': '0579', 'district': None, 'districtCode': None}", "summary_polyline": "w`zqDcs~{Ue@BODOLMRGd@?PLb@TXXH`A?~@Bn@EZULSLc@C_@KYIMa@O[Cy@AiABQBMFSVG\\?PETDRDJZPXH~@Dr@Aj@@NE`@]L_@?_@Sk@_@Ww@EaA@s@?a@LKHOZEPAPBRP^JJRJNDdAB~@A^C^SLQHQBQ?QK_@W]_@Om@C_ADQAU@MHUDQPMZET@PRj@RPr@Lh@@f@G\\@`@KVOHQFS?WKg@IQSMWK_A@_A@YBg@TKLEf@@h@NZTNdABdACl@?VOPYH]BOCQWk@]Ki@GmADw@AKDWVOj@@t@JXNFn@@`AAt@Ad@C^QTk@A[Ui@IM]Iw@Dy@Eg@EWF[TGHI\\Aj@@LT^v@HdA?v@@j@EXWJS@OAYYq@QOy@K{@?y@BOAMBUVMXEj@DLX`@NLZFbAB`AAZ?^UX}@?QKYQ]c@K{@AaAC]AWBKDQPS^Ar@DP^f@", "average_heartrate": null, "average_speed": 2.490519129193433, "streak": 1}, {"run_id": 9223370466971610517, "name": "Run from keep", "distance": 3336.086, "moving_time": "0:26:21", "type": "Run", "start_date": "2019-09-30 22:13:00", "start_date_local": "2019-10-01 06:13:00", "location_country": "{'latitude': 29.298656684027776, 'longitude': 120.09748725043403, 'country': '\u4e2d\u56fd', 'nationCode': '156', 'province': '\u6d59\u6c5f\u7701', 'city': '\u91d1\u534e\u5e02', 'cityCode': '0579', 'district': None, 'districtCode': None}", "summary_polyline": "i~yqDgs~{U}@D[AYF_@VMr@@LTr@XRb@H`@BVGbA?Z@\\OR_@@i@Ki@KQSKo@SaA@aAB]HUTQ`@CXDZFL\\\\TDx@?z@?j@CRCVONUBK?YIe@OUKI{@Mu@@{@?O@c@VOTG`@Bf@RZHFf@J`ACx@C^Af@QHIDW?YGUK[][ME}@IYAs@B_@JQJSXGPAVFh@XZVJz@@v@?|@CNEPQJUFc@?QCOW]YOaAEaADYDKA_@DQRINEd@V`APJTDt@?t@C^Bh@GLET[Jy@?MQ[_@YMEu@Aw@Bw@DYHYRGJCT?`@PZLP`@J~@A`AGn@DVITa@BU?UEQUg@WG[E}@Bg@CWEm@HYXITC^?RFZ^Xt@J^@REz@?d@KTONOL]@KAKSa@UUIOa@BaAAw@@i@BQHCHSZIZ?JBRLXTNJBZBPE|@?z@ATERIH?PSHWCU", "average_heartrate": null, "average_speed": 2.1101113219481338, "streak": 1}, {"run_id": 9223370466885798867, "name": "Run from keep", "distance": 3684.7395, "moving_time": "0:26:33", "type": "Run", "start_date": "2019-10-01 22:03:00", "start_date_local": "2019-10-02 06:03:00", "location_country": "{'latitude': 29.298445638020834, 'longitude': 120.09719807942709, 'country': '\u4e2d\u56fd', 'nationCode': '156', 'province': '\u6d59\u6c5f\u7701', 'city': '\u91d1\u534e\u5e02', 'cityCode': '0579', 'district': None, 'districtCode': None}", "summary_polyline": "m{yqDur~{USMw@B{@?u@BSD[ZQ`@?ZLb@VVLDfAAx@Ct@AXMTWFMBOAOSm@IIm@Se@CeABy@@YNSVKl@Rr@TPb@Jv@BpAIVA`@QJKHO@e@COO]WYo@IaA@YD[Co@PSPIf@?NBTHRXVZHv@Av@D\\CLC\\SZe@BOCk@]_@QIm@CIB}@@k@@YJOLMRITATDPFNPLPBLH|@CfAC^Cb@SNWBa@IWMQOKQE_AA{@?w@DYLGHGJEb@@LZf@HF`AHz@Bt@?f@KRQNq@C_@IOWWeAEw@?aA?WBWPMZCV@ZNZ`@Vj@Bx@E|@?L?`@SRYBMAYM]IMm@WaAA{@Be@BMBMHKLK\\ALDf@d@`@NDj@B|@Et@?ZEHKNKDI@{@EMMQ[Q[E_A@{@Dm@@UPKZA^DXZf@ZJx@@^@`AEXCVOJWFa@@SQ_@SYMI}@Gy@Dq@Bu@LW@Fh@?j@HVJPVTND`A@z@BL@t@K`@o@", "average_heartrate": null, "average_speed": 2.313081920903955, "streak": 2}, {"run_id": 9223370466836626277, "name": "Run from keep", "distance": 2516.1636, "moving_time": "0:17:41", "type": "Run", "start_date": "2019-10-02 11:51:24", "start_date_local": "2019-10-02 19:51:24", "location_country": "{'latitude': 29.298661838107638, 'longitude': 120.0971910264757, 'country': '\u4e2d\u56fd', 'nationCode': '156', 'province': '\u6d59\u6c5f\u7701', 'city': '\u91d1\u534e\u5e02', 'cityCode': '0579', 'district': None, 'districtCode': None}", "summary_polyline": "m`zqDos~{US?i@ZWZI^AVBPPTJHRF~@?|@Ex@Eh@ENUD_@Gg@EOSSYI_AAy@Dw@DYDWLIJEP@t@FPNRPJ~@D~@@r@HHCLKZON[Di@?WCSGMc@[u@A}@@aAB_@JYTILEb@F^R\\ZV\\J|@CdA?v@IRONY@k@G_@OUQMUGu@Ie@?GDWBaA?MBQNM^CN@XRd@d@ZhAD~@Cr@IVQP[@]Ce@GSa@]cA@aAF{@BWJSRIVBj@LZf@\\\\D~@CZ@`AERKPOLSBKKq@MQg@Yo@K_AB_ABU@UPGNEj@BTDRTT`@R|@?v@G|@EH?l@q@DG@K", "average_heartrate": null, "average_speed": 2.371501979264844, "streak": 2}, {"run_id": 9223370466798988289, "name": "Run from keep", "distance": 1705.3187, "moving_time": "0:12:14", "type": "Run", "start_date": "2019-10-02 22:24:09", "start_date_local": "2019-10-03 06:24:09", "location_country": "{'latitude': 29.298357747395833, 'longitude': 120.0968310546875, 'country': '\u4e2d\u56fd', 'nationCode': '156', 'province': '\u6d59\u6c5f\u7701', 'city': '\u91d1\u534e\u5e02', 'cityCode': '0579', 'district': None, 'districtCode': None}", "summary_polyline": "y|yqDks~{U_A?y@@_@@OD]XM`@?`@Rb@JNXP\\D~@?~@?\\CTMPYB]Ie@Qa@KMMG{@E{@B{@F[VKLGR?l@N^VVVFx@C`A@h@GVITWDYCi@IU[c@UKu@CcAHy@F_@\\K^F`@R^JLPJPDx@?|@@f@EXIHGFKHa@Mm@Q_@WSMCc@Ao@B}@?o@HSn@Al@FXHPRNLBt@Dn@A|@CTBXETMP{@FILFDL", "average_heartrate": null, "average_speed": 2.3233224795640326, "streak": 3}, {"run_id": 12190487028, "name": "20.08.2024", "distance": 4992.4, "moving_time": "0:30:21", "type": "Run", "start_date": "2024-08-19 20:00:02+00:00", "start_date_local": "2024-08-19 22:00:02", "location_country": "Germany", "summary_polyline": "eca~Hold_AO`@GHg@Lc@?_@Fc@Cw@A]@MDi@DKA_AAYIu@BOBGAK?IFUCo@Fa@@UDyABiAHm@@c@HQ?SCq@CW@ICgBDEAM?KFa@\\a@M_@UOAIMEBEAy@Co@?y@HeABi@Fy@CEBc@@[DQAcALKEIISCEG[?YEY?o@LWZUh@i@fBWn@CXI@CECDANMVANWz@Kr@CJIDDR?d@AJDH?ZBX?bAPvCBpAGn@g@pAIXEXAhEFp@Af@Hh@CTEDANBRCfAD|A@tAQxCQv@?\\Ef@@f@Ch@Mr@Dh@?LGd@IRW`@UXOXCJk@j@IVKJC?GEQBSQkAK]MSQ_@s@Uw@O[Kk@Ee@EEGU]q@SOI?INICGB[VOAKCgAs@UWGA[UCYEKOi@OaACm@@KT_@X{@Re@HMTSPGt@o@DKDU?OLmBLY?a@AAA??GDKDCD@H]JEDKReAHu@H_CFk@DeAAuALQDmBAeAQwAAk@?m@Bg@Ai@B_A?sAPcCDc@Na@RUVOH?LJJCDDDCB@BEDDLCFBz@@t@FTCbAFPE^?|@TV@VGH@PEP?l@YNCF@PCL@FJ@J\\FNHn@EXI`@GVIFBLPRAVD`@Bl@K`AKLEj@@XDFAF@FNNCt@?FCHDpAGRDf@@ZAXI^YDGFUV^VHj@I\\@@C\\B~@EF@L?RDHADEP?DEF?HNLGTJV@\\ABCHAPGT?PAr@DXENIPCVHHE?En@QPHBADBp@@DDFNJ@LH^JV@VEP@FEVCb@MHPHA@CLCXFb@?n@O^ALOLCLIT@PM|@WXMh@]DAFDBAv@a@TSDMTGDSDqASwA", "average_heartrate": null, "average_speed": 2.742, "streak": 1}, {"run_id": 12199231634, "name": "20.08.2024", "distance": 5348.8, "moving_time": "0:32:15", "type": "Run", "start_date": "2024-08-20 19:13:12+00:00", "start_date_local": "2024-08-20 21:13:12", "location_country": "Germany", "summary_polyline": "m|`~Hatd_A]?CE[?kBz`@zBm`@_@FDH?JQ@MACR]lAmArLEREFMaNC_AIs@KJOb@S^OJIP?ZELOv@MVMBq@OG@C@Ol@CDq@LWAcBLg@HMFk@B[NIAUKQEq@?s@De@AoAHG?YMc@DkB?i@D[CaA@k@Jm@Mo@?_@BOFc@GSBSAk@Bc@EgAByACu@DUAEDg@JSGg@AUEs@BGCa@BG@KJIVEZq@jAKLG@KFMPUpB?d@Kn@O^STITJj@DvDTvCBdAOn@Gv@IXORK`@C`@Dn@QjAA`AJf@?JMz@?d@Dv@Hd@@lBD^E`@@l@CJK|AQd@MHC`@E\\Sn@Ox@KpAGXEJEBGLA?C^GVe@r@ITYh@EBKBKIMAICWWIAS@OGQSe@}@_@y@YcAU}@Ye@KEKB[?e@XGBEAc@o@i@e@aAaA[q@Ie@Aq@C[F[Xg@Nk@j@{@RQNEXS`@_@V_Ab@gC~@uJHe@F_AEa@AuDIqDH}@AeBBa@FkCDc@Ty@FOX[XIZEbAJFATB^CP?p@Ln@?\\HLCf@HL@VCDBdAEF@PEd@F^Ij@Dp@Et@B|@C^Dd@EP@RAf@BbAEp@?VCpAFVEfAETB|@?Z@TE@CCHFJFA@GFAbAIb@Bb@CZB^Al@Kb@Cf@B\\CBA@EJA@BHDl@AJCf@J`A?v@E|ADj@EP@PGZAb@JP@JCzAIHCt@?VELBdA@n@Q\\O", "average_heartrate": null, "average_speed": 2.764, "streak": 2}, {"run_id": 12208132347, "name": "21.08.2024", "distance": 4382.1, "moving_time": "0:26:56", "type": "Run", "start_date": "2024-08-21 19:10:41+00:00", "start_date_local": "2024-08-21 21:10:41", "location_country": "Germany", "summary_polyline": "oda~Hmjd_Au@DYJU?K@SAe@IOA_@BqB@QD]?SKQDg@AyAL]Ec@D{@@k@Fg@Gg@BoBEe@?i@BOCC@CAk@?KDECGBYGDBB?ICwAAgAFy@AcAFi@@e@AWBy@AS?GDkABq@Hg@AS@WIOAa@DeAGeAHW?QEi@FQEmAD[Kc@Ca@AKG{@G_@OW@y@CCB_@Bc@HID[b@KZGXM|AA|A?bCOfABHBlABVBfB@nCEdAWbCUtCAx@Ef@a@fBQdAa@dBNGLMD]Do@^}BNiBNm@AINaA\\}F?_@MiI@o@HeAAk@AKBeBJmBDI@YF[L]LSZQXEf@?t@J\\HvAB`@ARB|CFb@?XGbBDdC@n@CjD@hACLEb@DJCR@PDhACNCpABz@CVIb@Cb@Hx@ENCv@D|ACv@BxDIZBzA@bAJv@Ej@Ml@AlABRC^?RDFEFDt@MvAGXG`Ag@", "average_heartrate": null, "average_speed": 2.712, "streak": 3}, {"run_id": 12216657808, "name": "22.08.2024", "distance": 4430.8, "moving_time": "0:26:20", "type": "Run", "start_date": "2024-08-22 19:14:02+00:00", "start_date_local": "2024-08-22 21:14:02", "location_country": "Germany", "summary_polyline": "gaa~H{rd_AWVELa@n@Kl@BPEr@Kl@MFCFMAw@Bc@HWBa@A_@IYAg@Dg@@q@BcBAc@BUDIDMTS[MCE@KJGGGCIB{@Gy@AQFI?YDYEGBo@?YDIAKBIEYEi@?KCUDq@BMA[DF?BKEOGAc@NUBc@AuAJ_@As@J]AsAL]?IKIBEICBICE@IEQBi@@MB]E{@Fg@GS@QDa@Ce@B[?WIa@Hi@ASBYAQBy@AQEO@_@Mc@DGBGCIMKAI?GDIEWB]AaAGy@F[HYRKTK\\Oz@EfAC~ADnBI~@CNBPB|BDfAA~@BRGrCMjAEdAKl@MzAA^OlAc@rB?FGDAEBOHQBYXgARiAFeBH_@LoBL{@JqACuBE{@IyDD_BGu@?{@D}@PcBNo@Xo@HMLGpAg@d@Db@FPAHCn@LZBFDRAvAFt@?NCl@Dp@Cd@@NCjABFBDJHBd@Ez@OJ@REdAN|@?n@GL@^A`@B^AZBJBLARBJ?TKl@I`AC^B^GNGJLNA\\Fb@Av@EX?r@EDHDCFFrAMZ?n@Db@GDHF?FIBBB?@BjAAPCTDX@^MZEt@FX?FCR@LCX?FAn@Br@Cd@BPCHBtAEt@G`@K^QNEVORAFB", "average_heartrate": null, "average_speed": 2.804, "streak": 4}, {"run_id": 12224635059, "name": "23.08.204", "distance": 2438.9, "moving_time": "0:14:02", "type": "Run", "start_date": "2024-08-23 20:03:37+00:00", "start_date_local": "2024-08-23 22:03:37", "location_country": "Germany", "summary_polyline": "es`~Hwre_AHjA^tAD^@d@?PGPE\\?HEj@@\\O`C@^ITAl@El@Az@Gr@UF_@TYLcA`AQJMg@WhBCME@EEG@@GKCI@KBOTq@RMP_@B]Fa@Ns@`AOd@Cl@Az@A\\EDIAEBSBsAH[AI@aAEm@HU@m@F_@?WD]Ik@DICm@CkAF[Fy@GqCA_@G_APa@DmA?O@}@?w@RCDI?AK?KZa@EN?Fv@LZ?^IhAK\\?ZDPAfABVAf@Ij@?t@M`@ClABdA]f@Jj@@ZFH?b@HZBzBE`@DLCXMj@IDDDHF@NAXHV?^Eb@M", "average_heartrate": null, "average_speed": 2.897, "streak": 5}, {"run_id": 12226921663, "name": "24.08.2024", "distance": 5031.4, "moving_time": "0:30:44", "type": "Run", "start_date": "2024-08-24 06:06:18+00:00", "start_date_local": "2024-08-24 08:06:18", "location_country": "Germany", "summary_polyline": "gba~H{jd_AQDS?GDwAFSFKGYDi@Cq@@{@JOCSDGCCDI?YGg@?_@DYTYBMMIEQA_@Gg@Em@Da@GEBWGSAMHK@ACI?_@BQCGCoABa@FSEK@OAWFQ@KCw@BOAk@OG?IBWBg@@q@AMB_@@YAMBADgAFq@CO@GAO@WGU?m@H{@B]DUCC@O?g@IUDGAc@@MA_@RGJK@EF_@r@KVYh@S|@q@xAENGt@ObA@pAL`CDpBAXBXBn@Ej@a@`BBJGN?PM`ACpABz@An@IhA?v@AbAPjBFt@?`@Gl@K`@Iv@Gj@EfAStAKjAA\\ERG@CACVc@`AQf@cA~AEBI@YAWGSMi@WUSUm@Q[CO]q@e@qBS[OMKCa@BKJ[VELGAWc@q@q@s@{@Yk@Kg@Ec@?IDKAc@^gAL[p@iAl@Wb@a@Tm@Ny@LaALoAHeA@c@HgAAk@Bg@J_BLo@FwA?eACUCw@BUCWCmA@OBGA[PsA?_BGy@?cA?c@Fc@B_AHUBBXSz@Wf@CDBj@BTFl@C`@FT?^Fn@Tj@CrABRCFHdAOx@BbAEPGBJDG\\CbABj@Dl@Ep@@lACZ@t@Cz@BREr@A\\CFG`@?bAJj@CXCDDX@XEHEf@BZABBRDZ@XCREN@pAGT?t@HVAf@Ob@Cz@DLFh@Iz@BDC\\@b@ATBL?l@CNEZ?NAv@DPA\\F\\CLC\\BXAJB\\CVKTEp@a@", "average_heartrate": null, "average_speed": 2.729, "streak": 6}, {"run_id": 12236466382, "name": "25.08.2024", "distance": 5040.6, "moving_time": "0:29:07", "type": "Run", "start_date": "2024-08-25 08:51:57+00:00", "start_date_local": "2024-08-25 10:51:57", "location_country": "Germany", "summary_polyline": "iba~H}kd_A]N?LEFc@VUDS@[J]?[FKFy@N_AA[G]AOEc@C]DI?WFeANU@q@C]BaACa@SMKU?w@Ks@CsAFSCQ?UEiAFg@JB?ZEK@i@KcADmABKBKDQCiABc@Hm@EKGS?_B@q@JEA_@@k@C_@@y@E[BMASGM@]CuANs@@o@EODUIW@IKgA?m@EKEu@?m@Eg@De@LU\\Sh@Qt@E^IdC@`BIt@Ah@@jB@^AjDBhA?jAEp@@`@MfCELGz@Cx@Kl@MvAIHSn@]n@s@n@MDOJc@~@]pAEFE?GD@REZ@pA\\r@|@rAVh@NFNTNDVUD@d@EFBLNB@Tf@H^RZVz@h@jAXd@TRZJJ?J@HCF?LEHILE\\c@JSPQVs@He@Fu@\\iAJYPaAViAVuCD[FQBYF{CCkAMeBEgBJmA?w@Bu@Hc@LsAHQJu@BiAA{AQsCGaC@kAFs@^uAJIN_@VSLULW@MLOVk@HKXU`@Kp@Gv@Bj@EX@x@Gr@FFCVDVANB\\AVDHAb@BRAp@Kv@A^GbAJh@CNBd@E^ITDVCLDLCDBd@Ah@BnAI`@IDMZNd@@^GV?VI\\ENGZBN?DCpAE~@Fb@HLAbAPZAx@Dh@A^IN?LC`@?n@GRAJ@TALGHIJCNO", "average_heartrate": null, "average_speed": 2.885, "streak": 7}, {"run_id": 12247363343, "name": "26.08.2024", "distance": 5004.2, "moving_time": "0:28:39", "type": "Run", "start_date": "2024-08-26 14:38:12+00:00", "start_date_local": "2024-08-26 16:38:12", "location_country": "Germany", "summary_polyline": "o~`~H{nd_AIFEBM`@Y^E@[@KOE?c@f@YR}@@SDEMIEMMe@S[?}@FmDl@WHcANs@@{@AcABi@HqAKm@BSDc@GKBU?qCIY@{@Ki@HgAFoB@M@k@@_@B{@Ca@@]B[CsAHu@GOBg@A[DQCaAFQEYAsATUCs@?YES?_@GQ?]GEEUI[?WGQAWBiAMi@HWLMHg@l@IXMdAAfA?dCKxBLpGAPF~@AfAQpCMz@Ab@U`C_@fC_@bBOb@U\\{AbAKLIRe@tA?NE`@@NR~@FJJb@^j@d@TPRJHP@PGBF@N@BFEPAl@Nj@r@@ABBNVh@p@^v@PHh@Hn@z@LHV@TEZAp@w@@MBGNoBBKFGD[dAoEFaADUB[I_C@y@EwAEY@aACUCE?s@D{@JYLs@DqB`@eECqAB]BGI}ACuBG{@@e@Jq@Bc@TaA`@gABWFQZa@N_@T[Vi@FKHENIh@G`ACv@BXCFCdAJXCHBBFB?FKLCBBH?h@EFHl@KV?LBREj@BLFLMRGLB^@PAt@DJDNAP@\\HL@dAUZEFDD?DE@@r@AXB\\?TDPARGX@FCz@DpAIx@DHAXHFGD@DADBHHRSFBb@K`@CNCLFLA@IXJZDf@Al@DNCb@Db@ER@PJ^FRAPGJGBK^FTGTKp@c@", "average_heartrate": null, "average_speed": 2.911, "streak": 8}, {"run_id": 12252406161, "name": "27.08.2024", "distance": 4986.8, "moving_time": "0:28:45", "type": "Run", "start_date": "2024-08-27 05:53:54+00:00", "start_date_local": "2024-08-27 07:53:54", "location_country": "Germany", "summary_polyline": "eca~H{jd_AKBaAHo@L]AqBDg@F[Ce@@a@CYASEY@s@L}@RW?SCaACUIc@SEAo@Hi@Au@Bw@AKCMBg@?}@DMAa@Ha@Ng@ISAe@O[Bo@CUBWAaANo@Co@BaACu@Fe@?m@BIEOFICU?ECa@Cc@Ai@BKDe@@a@FSFe@AY@GFKBc@FOAOKMECIOCYSKCU?i@BaAKaACIBKEWAs@LYZINI\\@rAOfACj@@d@H~@Bx@Gp@@XKt@E~@Bz@GxA@X?bAQnCWxCGVA^CH@r@C\\Ov@AXKd@?NIVE\\M^GFy@l@[L_@j@O\\OTG`@Mf@Af@E\\FlARb@`@d@v@^l@x@NBFJ@LJUFGXBJA\\H@J\\x@FZXz@^x@J\\HJBNTJNLf@RXHP?FCTMHK`@m@N_@NOJUNy@VcAF]HQAWP_ABoAVwANwDDSDcAAiAAs@Ii@Co@CaA@{@FW@O?eADm@Ha@Vm@L{@A[@iAKgA@_AKaB@UBSGo@@YN}APo@LmAH_@`@eAd@{@Tg@`@k@r@]NFBJ^@HBfA@TE~@EH?HDZAXBdACr@BFAB@FHDBTCHIJET@HCrBCl@CHBBCXBA?@AFEBFLFd@D`AKb@GLBNCx@?~@GJBHCZBVEDBVE`@?LBFE\\Df@CbAFPCH?LE^Cn@HHAJBZCBCLBF?BCB?THd@CN@z@Kz@@\\I^?FDFENAFCPDr@?NER?\\EVI", "average_heartrate": null, "average_speed": 2.891, "streak": 9}, {"run_id": 12261660294, "name": "28.08.2024", "distance": 4983.8, "moving_time": "0:28:44", "type": "Run", "start_date": "2024-08-28 06:15:33+00:00", "start_date_local": "2024-08-28 08:15:33", "location_country": "Germany", "summary_polyline": "w`a~Hmkd_Aq@Ro@?e@HG?ECUBIDAA_@AmA@QBMAc@P_AEc@Bo@A}@Fk@Am@J[?ODa@?MCmA[UBIAW@SCq@Hq@@k@AIEIDe@Bs@AECYAe@DQAgAF_@Ki@FIEM?uALi@?YF_ACa@NEAQFk@HGECISCUOK?G@SIk@DmA@MHQDQ@MAGLSRSj@MBEFUb@c@l@GNc@jBSlAEbCGZFl@LbDDd@?~AKjAQn@OfA?RGb@@PGRBVEhADvAGj@B\\?d@BTBfBC^@f@KrBWxBCl@@LCTGL?ZWpA[jAE\\Wx@k@|@MZ[b@]BY?KIy@]QSu@qASu@CQCIE@?IU{@Qa@YIo@DUHMC_AgAu@q@UMGKUk@MkAAo@FI@MLMf@wAJWVQTUTGRIX[FILy@LkAL_AP}AJ_BJg@DKRiAFm@FyA?o@Gi@Cg@BiBCm@Eg@E{BHaB@cCD_@DSDEASLYXqAHKR?JINEv@Ep@@N@h@?H?FENDfADb@HfAF^DdAAn@IX?H@FAf@DXAPH\\ORAf@BFATDJAVBXEj@AnAHb@CH@ZE^BDGL@VGRH\\@HEp@Kt@Bj@GZBNEf@YFAF?h@PZBTHhAA\\EJEXFX?b@FJAPKn@E`@QNEH@NGRFXAHVF@XELDH?p@N\\CVB~@QN?DDJAd@BDDHCDMTLNEr@Ch@DX?NHF@Z?HCbAB^]NCJGZw@", "average_heartrate": null, "average_speed": 2.891, "streak": 10}, {"run_id": 12270220637, "name": "29.08.2024", "distance": 5038.5, "moving_time": "0:28:54", "type": "Run", "start_date": "2024-08-29 05:44:40+00:00", "start_date_local": "2024-08-29 07:44:40", "location_country": "Germany", "summary_polyline": "cba~Hood_Aa@LW@w@^c@@Qh@UBK?GHCHe@DUHOBMHOGOBOG]AS@]FYNKCa@Fq@`@{Ep@n@OAC_@AIQIEMAi@?uANM?GBOEY?ICGMGCY?i@@{@Nc@@k@P{@M{@Ei@BwACaA@MBgACWB]?e@Js@@u@Jg@E}@EEAKMM@YGWB]EgBDi@Hw@@_ACg@Dq@I}AASE_@C{@FMDMNK^W|CAhBDdAKr@I|AHtBCnBDp@AjABd@Ef@EnAIr@@RKl@A\\OlASjAWjACTOb@Mh@oApAk@\\i@f@U^Sh@Ij@C^D|@Pp@JBNL^LfA~@f@j@NJF@DANQXO^ER@FRDDBFDh@Np@FFb@zAXp@T^LHF@^RdAVFAHGl@w@Vi@h@wBN{@JqCPeA@kADCJCDCNcAAKLoA@sAUaCKa@Iu@?QBuAB[\\wBVm@Dc@B_AHMEa@D_B?{AEuDGsABMFa@Fo@Nq@L[@_@DK`@q@L]Ry@l@}AHKPERBbA?b@CN@NEbA?RBb@Hd@?p@IJBXAh@LJKFBVGdABn@IDBHE^?RBr@Aj@ME?d@Dt@E^Db@?fAERE`@Lv@DHB\\?VBHBNEPA`@N^DRAjA[H?PDNCDCv@?pAHTCP?FIHCp@?d@IfA?PBXCp@FV?f@DXAHCLIb@K", "average_heartrate": null, "average_speed": 2.906, "streak": 11}, {"run_id": 12279609091, "name": "30.08.2024", "distance": 5033.5, "moving_time": "0:29:43", "type": "Run", "start_date": "2024-08-30 09:07:57+00:00", "start_date_local": "2024-08-30 11:07:57", "location_country": "Germany", "summary_polyline": "k~`~H{jd_ASVI?OPq@VIAg@J_@?}@HE?i@Qg@Km@IgACk@Fc@@uBQW@MAkAAq@JY?a@Eg@F[HYNOBw@?WCm@Aq@KkA?q@IOEi@EkBFGBk@FWAWBaA?u@DaACMDg@GI@KD}@BOBOAO@u@E[Bu@IKBMCs@Hw@Ro@D}AQ[Ik@GQGQAMEgAEOGu@E]EY@WAq@PGLOJMRIf@AXIf@?\\EjA@hCIhAClB@tA?ZBv@?nCC|@MrB[pCMfBOt@Mb@K`AKd@KV]b@cAf@YZSVg@lAMVGb@@PRdAHTTd@JHXj@bAt@b@j@D?PEVOL@f@GF@FDZl@Vx@FX?LNp@r@vA^^ZLz@NPCXWBSLO`@_AZi@ZsAHk@Bm@PsBHe@Fy@Hg@HYHs@Ao@GaAJaEIiBAaAHuA@}@TuALc@?WHc@HkAI_B?q@IwAEqC\\yBV_A?OFc@LSh@yAhAiBHIJCx@Er@Lz@GXEn@?j@@FAZBJCZB\\EH?HDXCx@HHGRAZ?ZBp@El@A`@Db@?f@RNOr@Q\\EVBf@AHA|@EJBf@Cr@B`@G`ADDEr@Dv@CPDV@VMH?\\BRATDj@E`@B^AZDj@@XBZABGNBPCLFf@?z@IV?f@GL@FANIf@M", "average_heartrate": null, "average_speed": 2.823, "streak": 12}, {"run_id": 12287626379, "name": "31.08.2024", "distance": 5024.3, "moving_time": "0:28:54", "type": "Run", "start_date": "2024-08-31 09:14:59+00:00", "start_date_local": "2024-08-31 11:14:59", "location_country": "Germany", "summary_polyline": "e`a~Hald_AODSNODO@WAQB]FGFa@HYBWCMDS@iAKWFk@Gg@Fs@@GAOFa@F}@VY?EMQD}@C{@BGAIBe@?s@U[A]IYDWA]@ECS?KBc@Ig@?IAe@FW?W@k@CWIU?_@DWAQEWFQB}@@g@HSAYBiAJI?CGODY?[Ca@?c@LOEI@QCI@YEY?_@DCAACYAI@WEOBSHQCEJ_@M]D]ASBc@?WD_@I]?k@Q]C_@De@EOB[Ci@MYBQAMBa@JW^GDKAM^GXMbBG|ABhAA~@KtAJ`C@hAARDJCLBb@?n@ExACTGzAAtAS`AGz@Al@G|@AJWd@[dBIVMX]`@GIMD]D?@a@f@QVm@bBIdAFl@Vv@NRHRJNRJNIDBDTLJFJ@HR^NLD?DBNIr@OPCD@FJDRj@~Al@lBXr@TVNLJB\\BRBFE@DP@PEBELATQHWLQPg@Ve@JYB[HK@QN[Da@VmDNu@@]J}@BaBEY@MJM@qCIkBKsADODs@HmCPiADKFKNuADi@Aw@W_EA}@DQAM@ICc@HYZkDPwAJi@JQd@k@Ra@n@}@JCHNF@JENFj@A~@It@@\\E\\DFCV?TFDDVCT@DCPBj@ELBPEt@@NCPBFANBDADDZEx@CZ@NEb@CHAf@[VDDANDZ?PB|@GRDBDFC~@?^GL@F@JA@DHD`@@\\EHDTB`A@XCJETB\\AF?TCN?h@KVAZDHAFFDCb@DXC`@?`@EJDJCb@@ZEPLJ?zCOTKNE", "average_heartrate": null, "average_speed": 2.898, "streak": 13}, {"run_id": 12296017701, "name": "01.09.2024", "distance": 5124.8, "moving_time": "0:29:38", "type": "Run", "start_date": "2024-09-01 08:47:01+00:00", "start_date_local": "2024-09-01 10:47:01", "location_country": "Germany", "summary_polyline": "c`a~H}kd_AQPk@TWFGEYBSHq@He@Je@BEDKEQAUK]Iq@BIBy@?E@c@A_@FSH]Jm@?c@JU?e@Hm@?i@KQAGDMEm@?}@SOGu@KIBQCQBK?QF[Au@D]Cg@JAMGGu@HaA?mALSCc@?QBe@Go@BMCg@BIBu@AGCEFIEE@QCk@HUE]BMC[AI?EDWCKBS?q@FCCYAW?[GUH]?c@Gk@BYCS?{@I[@EAg@BCIMIg@@m@GaABUFID]l@Mj@S|BEtB@n@Cf@Ib@C~@HzBAhBFbA?vAGdAKv@Cx@WnBCd@_@~BAV]zAW|@a@Zg@VUVIN[~@_@v@K^C\\DjAD^PZ\\b@`@Th@RLPLHLBr@MTCRFHLXt@BRLRf@tCH|A?^Bn@Af@IPA\\FAJOVALK^STWp@g@`AiAXc@Zy@NULk@HOVmAZqC@g@Ds@BOHC?UHa@Fi@?s@BuAEyAGsAA{CDiEBOHYl@uAFc@A{@Eg@OiD?k@MsB?g@^{BV{@Jy@NIHQFWN[`@m@l@kADE`@Ah@IX@RDvAGTBfACjAMn@@`@Bl@EPFDA\\@XFX@h@ELIv@CFJFAv@PIGYMvA@jAItAFDFDCJ@NGzAAd@KlAKX@JFL?`@LV@tAIx@O~@G`BDJ@FFH?HFF@x@Gj@?`@BtAG^IZMh@a@", "average_heartrate": null, "average_speed": 2.882, "streak": 14}, {"run_id": 12330175113, "name": "05.09.2024", "distance": 5016.1, "moving_time": "0:31:58", "type": "Run", "start_date": "2024-09-05 05:37:34+00:00", "start_date_local": "2024-09-05 07:37:34", "location_country": "Germany", "summary_polyline": "o`a~Hqkd_AWJo@ZGIc@JOCKEg@Ao@He@AQFKCe@Dq@BICQKKCc@FW@_@D[@k@AuAHYCi@Bi@KmAB[A]DQIk@HSAe@BIAe@DU?OB]?YECDC?QE[?e@GOEYDk@AUDCDEA_@DQCSBQE[BQ?I@GFIAGEeBBi@KYDQAk@JECIFIEM?]Bk@@YA[DKCCECDC?QCSBmBCUBc@?SFCCc@B_AMc@Ca@Mu@Ak@SIAWDkBAKFG@Y^Of@MnAG\\@PCv@?dADh@?ZF^?\\?f@CP@b@EfC@H?hCCdBGr@CfA?dBCf@Mf@IbAEHE@CD?FSt@Q`Ag@|BQTi@b@]P_@^k@bAOf@AL@f@Fr@Fd@Nh@LTHDh@n@NHl@x@FDH?TG^YLEPAP?TLDLENNTb@rCx@zAPBNNTNp@JNBLGFGJ?HUDABE\\eA`@{@\\gAZwBJeB\\gCFMBeACUDcACy@@}@AyAQwC@i@TcDHe@Zs@Ji@AIBYC_AC}AI{AAqBEYBm@\\oCL_@@]HQVuAHMNi@NSLc@NQNMLQRCNJFEHA`BJh@Gt@FtACl@@HEXDHAb@@VEFBHCR@XGT@PDv@BPCn@?FEP@FCd@AZMEDDFFBV?vACjA@TE`@Ev@BzAIHBZCl@BXCX@TAHBFAPK^F^?\\GZFZBZIPA@E|@INDRC`@FPARBd@Ax@I`@FXAT@HAD@BDHEBG`@KJKFAF@ZODE", "average_heartrate": null, "average_speed": 2.615, "streak": 1}, {"run_id": 12338442138, "name": "06.09.2024", "distance": 5078.4, "moving_time": "0:30:12", "type": "Run", "start_date": "2024-09-06 05:45:18+00:00", "start_date_local": "2024-09-06 07:45:18", "location_country": "Germany", "summary_polyline": "o`a~Hcld_AQLgATc@@w@Eq@Hk@AM@g@LM@e@?]Ba@OS@UEWA]FUHECQ@UFq@Bm@?_AKo@HUAEE_C`@yA@UGUCYBo@Ac@BYCJH?@CDGEMAm@AMBc@GW@_@Gw@BGBYDKEGBMCK@IAi@Bq@Io@FUAg@Fi@@WCy@B[?c@EK?EBOAWDmAI[@c@AIEa@C_@FIAQDM?]FCA]?GCS@w@OY?GBCCWG}@EM?QBQA[DKAKDG?SJORO\\WzACh@G|A?h@Dx@MxA?b@Br@Fx@DvBJnB@^MJBRI^E|@a@tDCrAKrAMv@OrA_@lAKRQJKKG?MLo@Zk@l@Q^W|@E^B`@JR@Lh@jAR\\HDPZ^NPd@FLLHBCD@X?JEl@IP?FDZx@JJBNBFFDFVFFNDHPDPER?ZJLF`@@BBABJJLl@\\b@HJ?HEHARKNADCf@}@Pe@Jg@Ra@@IFE@GNaA@a@RiBHqA`@aCJaAKk@BIBk@Gq@BaAMsAGeBHyAJo@?w@Nm@\\o@DYCq@HwBCK@YMyCIo@@S?uAD_@\\yCNu@ZgAJWPSLYX]DCDMPWLK^KXCNBf@Ef@H`BAf@FFEJ@b@GF@j@?x@GXDXKDHD@FCb@@ZJb@GR@\\Gv@@PCHBZ^QOHONCb@DJATCn@EBCNCVJT@FCz@GP?r@KZAR@XDJAHJV@V?PGHAXBHCLBJ?@CVNR@VAJEt@K^@PGf@@LCRBb@An@SNPB?@CRD`@?XDRAPBZAd@@x@Kl@YZKFEFKNE", "average_heartrate": null, "average_speed": 2.803, "streak": 2}, {"run_id": 12355119111, "name": "08.09.2024", "distance": 5366.4, "moving_time": "0:33:34", "type": "Run", "start_date": "2024-09-08 06:45:54+00:00", "start_date_local": "2024-09-08 08:45:54", "location_country": "Germany", "summary_polyline": "cia~Hsvd_ACRCj@@zAG^ABI?WHETG~@Bh@FBLZb@V`@HnA]h@CZBVCPGHIBJAFAHKLOAUIo@Jc@?[Fc@C}@Hw@?SGc@CIDKHSEU?i@FI?o@Mq@RW@WCM@KE_@?aADQASDaASk@JICQBa@ES@IAQ@[GYBGHWA[D]A]@QDg@Q[C_@BGDu@A_AIm@LY?k@Fe@GGBy@A}@?SEi@Ey@FQFEFIC}AHY?GCa@Cu@DIAWDW?u@IW?QCKBUIEDKEUBa@?]EWIK@SAQGQ@ICO?a@GM@GDKCEBONg@XONGPCVOlAG~@A~@GzBIv@?NFbA@jADd@BlCCtA@RMbBAJCDQdCO|@Gh@Mr@M`AWlABLKRC^]f@[RYFOHMP_@v@Gb@Kd@?VGFAF@PEP@JCVJx@Ld@R`@HFD@LNRLTXLXFB?FJHRDP@RSTKPAZD`@l@JT@^HNFj@HZb@fAHHJR`@^ZH^FF?FENDPOLGLKPUR]`@mAR_@DWZyCBu@NwA\\_CPsBBi@EcA?oAMoBCoBNmB?m@V_BHYFm@CcBBgAAMCG?IHECQG}@@eAIsADs@bAuELWFUT]f@mAb@c@@ABBHGd@K\\CFFB?L@HAh@Bp@ALBrAABCl@@v@KjAEFHFCVBxAE~@FXGP@DCP?RAr@S`AVFCt@@DAl@AD@LA\\?XGPDZCPDHAXFZCJGl@AXEFFBA\\DhAAb@Jd@BjBUDGN@HCTFDADDDCDBF@TGPDr@El@MNDNAH@^CDBf@DZAHCNMd@K", "average_heartrate": null, "average_speed": 2.665, "streak": 1}, {"run_id": 12384099666, "name": "11.09.2024", "distance": 4983.6, "moving_time": "0:28:09", "type": "Run", "start_date": "2024-09-11 14:20:35+00:00", "start_date_local": "2024-09-11 16:20:35", "location_country": "Germany", "summary_polyline": "cba~Hqjd_AMDi@?]Dw@?OBcD?qAHcAAe@Hk@N[BEAg@BGEIBa@GSKs@Os@Ce@BWE_BD[AIBCA}@Dy@GeBJoA?aADu@GqADm@Gc@@{@Po@CGB]Aa@D]?OG[AMGOAm@DYHWDi@Pc@J[CiAFe@AkBBm@A_ASG?QKK@g@I_@Me@GQ?CBKFQDOLUj@Ij@IdAAz@ER@V?`BEvCRfG@vBCZEHC?Md@Gh@WjDK~BUtAa@|ASj@m@x@o@R]XQXc@bACVAl@Dp@ZdALNdAn@LNLZZF\\UNENATDb@RDR?JVl@RjA^|A^z@b@`@t@ZBGJDb@?DEHADWV]^cAHYPWH[JaAF]?MHI@@Jq@Jc@Dw@FWB_AVgB@m@FcACa@AaAG[Gy@?OHMAW@_AJuB@sAEqB@MLk@D_@PaAAiADeA?uABOKeBAg@Gi@?SNaAFcAPa@PyARe@\\g@L]T[f@Q^CZIt@Gx@NX?HAv@Dd@Av@Ix@Bb@AZAPED@`@G`@@REp@AJCZ?h@Bp@EHCHOVu@FDDXf@j@LFr@DxBAzAKd@@BBH@h@SL@v@?B@RCX@JAPB\\Kb@ETBJAJDXBh@?PGx@B`@DFFBLF?FC|ABDCXBZ?TCTBLEr@ENGXURC", "average_heartrate": null, "average_speed": 2.951, "streak": 1}, {"run_id": 12408417136, "name": "14.09.2024", "distance": 4882.1, "moving_time": "0:29:16", "type": "Run", "start_date": "2024-09-14 14:08:12+00:00", "start_date_local": "2024-09-14 16:08:12", "location_country": "Germany", "summary_polyline": "_ca~H{jd_Am@H]?u@PUK]FwADg@FeB?o@GQ@cBh@gANs@I[Sg@COIS?eAKiA@UBWCwAB{@Fu@Pa@Ek@MEBcAAaAJgDIkA@wALwAD_AEUEa@?m@Bc@CWIqBA_AE[G]Ic@Eq@?sAMg@@q@HSNOTO^YhCAtADfCEh@?vAIdD@rCIrCEv@c@xEKz@Eh@WxBKd@IXYf@WXMNa@Zg@h@SZM^OdAAXLhAR\\v@~@DJRPNPNDTSHAbAHVLZb@DLZnAv@rBNTPNpAb@F?d@KPKVYd@cAb@eBTu@f@eCTcBLqAD_BB}AS{IDoC@i@Fg@ZuAPaBFyAEqCImBIaA?_@L}@VgATy@n@mAz@uATW\\W^Ih@CJCZLNBb@DVALBN@PDLKdAQL@FGDDPCjCL`AEv@LdAORAB@`AIXFLALFb@@HBLCd@AJGBIj@BRCnA@fBS`BAPEXBZ@XGf@EJ@BAR?JBJ?ZHn@H`ACb@DnAIxABd@CZ@XERO", "average_heartrate": null, "average_speed": 2.78, "streak": 1}, {"run_id": 12416446164, "name": "15.09.2024", "distance": 5122.9, "moving_time": "0:28:51", "type": "Run", "start_date": "2024-09-15 12:44:23+00:00", "start_date_local": "2024-09-15 14:44:23", "location_country": "Germany", "summary_polyline": "u_a~Hoqd_AILCLc@n@OPGNMCIPGBCAMZG@]z@SN[FOGBDEDUK?DKDMMMPe@b@WLc@FiAt@GCAIICE@YJMLQFq@Lc@NMBQCMOSi@MEaAQ_AAyAi@O@gE_@_A?eAF_BRk@@]Do@BkCIaBDo@CeAJ{A@SBq@@[Cc@Be@AwAPYNI@QC[@e@S_@Y_@Qc@GoBMaAAe@@SHIFS\\Kf@Eh@B`AAX_@xAE^?l@B\\Gn@AjANnC@jAApASnDi@jEU`C[rBe@pBEJKMw@h@a@d@c@l@Uv@Sb@K^CXDp@^d@z@r@NDh@BXDLJ@PDBb@L`@@JBRJRNVZ`@t@r@fBPZZZh@fATVFDNCx@q@PYXu@Rq@Jg@FqBH{@DqA~@mF\\_E@wACaCDiBGgA?aCDu@D_CR}ADs@C_BYmDDcAJ}@Nm@XeBVa@DCFBDDF?Ra@NQjBY\\AhAJVR\\Af@BFAFGFO`@O|@At@BnA@nBGn@@bANPCXH\\PR@rA[ZMxAM\\DZ?`@G^On@@NFBENAb@Ld@@RD`AC^GX@b@Hl@?PB|ACHA^At@BjBM`A?t@Gb@I", "average_heartrate": null, "average_speed": 2.96, "streak": 2}, {"run_id": 12433568531, "name": "17.09.2024", "distance": 5051.4, "moving_time": "0:30:31", "type": "Run", "start_date": "2024-09-17 14:38:41+00:00", "start_date_local": "2024-09-17 16:38:41", "location_country": "Germany", "summary_polyline": "m_a~Hsld_AQHADUNu@ViALGBCF_A?QF]Bi@CuAFyA@[Em@CSCSGEIM@GCeAG{@JWAOBgAPYH}AL]EgB?oACKCq@Rk@?KAOKM?g@GiABO@U?YFq@?MDOCS?SDIAOBy@?IIGAG@QA_@?QEQ@GAuBJg@A_@DKAWBIAYJQAc@Hw@C[EW@CAEEAGYDa@Ku@Gm@OyAOY?[Ce@Bs@V]j@QbAEv@AtA@PCN@XBJ?|@Af@IzAF`A@nAFnAAjADp@E\\IfBQbBIzA[|BUj@S~@]lAMTMJi@ZQRKFQVWf@m@dBM`ACZBVHVZ|@LLDDH?LJ@DPHb@Xf@t@TPT@RG~@ELD?JFHLf@Rj@X~@Pz@v@dA^XfARJGNITSZi@LOT]Vw@Jg@P_@Lw@HeB?cAZ}BEK@IBGBADW?IHu@F{A@uCAUKUIuCDkABO@kA\\eDHS@KAc@Fu@@sBAOEIAU@m@IwCNaBJe@Ac@FGD?D[Na@j@kAd@s@b@e@HK@KTONCN?FCP?l@LT@NE|@Hr@QxAFb@AHEZAFBVCr@BBGZDXGn@En@DPDREr@CBIF@LNFDBUDGDAzAJ^?d@E`@Dz@A~@LVEr@G\\@P?b@DlAGh@JLCZBFCBMD@FAD@`@Er@@ZEl@LHAbAH~@Cj@HHOJCD@r@EVMJ@DEf@MVO\\E", "average_heartrate": null, "average_speed": 2.759, "streak": 1}, {"run_id": 12469291061, "name": "21.09.2024", "distance": 6030.9, "moving_time": "0:42:09", "type": "Run", "start_date": "2024-09-21 16:30:48+00:00", "start_date_local": "2024-09-21 18:30:48", "location_country": "Germany", "summary_polyline": "iha~H_id_AS@g@EkA?}AGk@?aB?{ALS@IC]Dy@@]C[Iw@I_BAiDNq@Hi@BWKKQYSk@Oi@Bg@JoCV}@?OBk@EO@eAEg@@e@AmCBwAA}ABs@CiAAmD_@s@Bc@JGFKPOb@CP@XEV?\\Ch@YjBQtBMx@@fCDlBDtCMhC]hE]pCOp@UvAQj@OV]Rq@l@gAfB_@t@K@uB`@O?OCEB]AqAX}@Hk@@QBQJe@JO@k@EMDI?DCBHJFH@\\In@]RGrBEbBWN?JBd@@p@GNBVIB?ZLTf@`@d@FNj@n@~@bBLPNBRM`@Ab@?FDXd@DRDCHNb@hDDx@AfAQ|AITSVg@`A?JHLRv@HNFBH?LS^]j@]t@Ul@Ov@e@Z_@Ja@PSXk@V[TMXIL@LCLDv@b@dBH|@MzB_A`AcBZYXc@hCuCJU_@sCS_CGoAc@aESgCIu@Us@QyAMsBC_AKgAm@yFQ}BO}ACICk@KwAAg@ESIoAUaC?M@GTO|@E~AC`@B~@?|AItBBt@CbAB`@C`A?b@C\\MRA~CDbCE\\Cl@@PGn@GT@p@Jh@@rACfADz@E`@@NB|@C|@BnBGd@G^?vAk@", "average_heartrate": null, "average_speed": 2.385, "streak": 1}, {"run_id": 12570815001, "name": "04.10.2024", "distance": 4500.6, "moving_time": "0:29:39", "type": "Run", "start_date": "2024-10-04 08:58:01+00:00", "start_date_local": "2024-10-04 10:58:01", "location_country": "Germany", "summary_polyline": "cv_~Hqrd_AALCFEb@KDEPKNUp@CL?LFu@Ce@FW?PDB?HBAFi@DG\\RZVoAqASKUIYOYISC[OSYi@oAGIKCM?QEWMAQSe@KIYIEGCODUNqACIME[YMEGEz@kBGIc@AKGQ[OMGBOLw@\\c@h@c@jAc@dCWP[BKEEKB[Xc@Fq@?o@Cg@BSCWIY]]@SRg@RFHJ~@l@?TGXQvAMxBBVTHXDf@ERF\\BVFb@Gh@FDAFI@KFKBIEs@D}@HWVQBG?WKi@Qi@SKWHUZKFEJIFKCUMO@Y`@]L[EGLIZWfCKj@IHEAa@DKGCI?_@KYE]Bs@Ai@WkBISAUCGFa@DERCJSF}@NaA?OD]@QM]Di@EoA@e@Pk@N_@Za@JWJk@NW\\mA^SNJNCp@`Bl@nAZnB^zAVt@PVRd@Pn@Jr@\\j@FR?XALQ\\C\\KPYLg@Lm@X[r@ERC^JhAN`@h@\\FHN\\JFJAHBh@v@HTLTBNCHEFGNOp@Q\\c@ZIBQNI?AFOc@EIQEw@w@IEc@?QGk@Hu@Ta@?IBc@?i@FI?CA@@WQY}A`A]DQAeAFe@MqBB{CH]FBHCBGf@gBPg@BMFDDE@G\\\\h@PT@^FLCFIFSDcAHWTc@NUDDPALQDUB?ZXDJFRDn@l@vATz@FDFG@Ff@h@HRH@@IHUAOBg@Ra@TYNCROZK^c@Cm@Pm@HQDe@Qm@", "average_heartrate": null, "average_speed": 2.53, "streak": 1}, {"run_id": 12598161342, "name": "07.10.204", "distance": 10641.1, "moving_time": "1:10:37", "type": "Run", "start_date": "2024-10-07 14:02:53+00:00", "start_date_local": "2024-10-07 16:02:53", "location_country": "Germany", "summary_polyline": "ch`~Hubf_AWVFx@@l@Wf@]^Gv@S\\M\\UhCUj@E`B@RRXl@^Jp@QpAQ`AUl@SVQHIPQt@Gf@Cv@b@hABRGj@?fAB|A]bA[`@Mb@_@r@qA|A{@pAQb@IEMLi@Gg@VgANOH[h@QPo@HaAIS^SDKNo@Tk@\\aALq@_@eAGMMEO@YJaADoA?KEGmA`@_@QSAON}@QON_@?WMuANi@C_ALo@Ia@D{BMqFAiBHe@KkDP}AGaDJaBKa@J_B?u@HyAKy@Fg@KeDG{BO{@d@e@x@U|@F~@EvB?~BIz@JvCFnFW|Dk@xFe@|AOlAKb@g@f@k@NYRk@dAm@jBCd@@VZfA\\j@hAn@ZZLZPNLBXKh@_@XHRj@XlBj@~AHPXFx@x@RDXE\\\\FCLQRm@Z]Pu@Xu@`@_CRo@RiB?s@De@`@oBMwANiD?y@Is@?q@DiBHy@AWIs@LcAZaALyB?g@]_H@q@T}AV}@VyAb@o@Xw@ACJGXm@LOt@?fCYzBT|CAhBQ^RTSj@JfCId@Fx@]n@LhAEz@Lp@OxAIjCJnCUdDThAEpBJlAA~BmAhAa@f@[n@Qv@{@T^^rBDj@VhAQWF[NOh@K|@y@f@{Av@o@Nk@b@o@ELDED[LO@SIc@?YJwA@sAFGl@OJKb@iCF{@VwA^Dl@NZPVAp@b@jAEpA_@PUDo@CkBs@eDaAoBw@eDWu@kBsCKEu@j@a@p@a@lBKx@Cx@k@fBD|@Rr@`@d@L@NN@lAKdAUhAs@dBe@~CBPVTFX?pAO|A@ZVj@F?^e@p@EfAa@dATZIRNLv@Rn@b@h@d@Wt@{@t@iAZAv@Xn@Dh@\\Jf@R\\ITCl@OZ?TCRWCCXVVFE@]G[Cg@Vg@HEZTn@DfAtAVl@AhAM`AoAvD}@vAy@hBUz@ALFXCL{@dBoAnA_Ap@_BfAwBhCyAnA[R[D}@t@GQC]S{@MeAQk@]gCUcAGw@Wa@Qk@OwAYiA[cBKy@BS@kAEyA]oAV]XHn@_@Nm@V[\\oBXs@d@_@^S@]O_BRe@L_AAQI[CYUaAC}AHw@Pa@@Wn@_A\\sB?w@EUQSo@gAMi@NYLq@RgCPgANWVANm@LW\\YDw@", "average_heartrate": null, "average_speed": 2.511, "streak": 1}, {"run_id": 12630064041, "name": "11.10.2024", "distance": 9475.0, "moving_time": "1:02:35", "type": "Run", "start_date": "2024-10-11 14:36:09+00:00", "start_date_local": "2024-10-11 16:36:09", "location_country": "Germany", "summary_polyline": "kg`~Hibf_AMCMdAON?DFIa@v@q@v@]p@BP?f@Et@i@zBE^?h@Lb@Xh@^NF\\FHARDXQrAY~@OJKr@k@rAOz@Eb@BX\\h@B\\Ij@Ah@BTKv@k@bBIh@IVMGOf@UNAHa@WK?HrAIXYj@]f@o@f@CQSa@Is@Sa@Gm@@_@aAXUECDEAIQKEUZk@Pe@VkAz@UAOHCLGF]N}@J{BFgAP}BM{AJw@IaAFy@IqANk@GOQOR{@BiBGaAJSEKQOE[Ly@J{ALq@A]H{AQ_CBg@FiACWI]?[Hm@I_AJ_@CQk@S`@MLQGq@BYCKUG?]\\]?eA]EA_@RQ?UQMDg@MsAEm@Hs@TWTW`@KZK\\AZE`C@|BIr@AZFx@@nDFhCEhBWpC_@bDU~@Et@Kr@]|AY^GRMHSDCJIHYh@M?UTS`AOTE`@DnB\\|@Zf@n@Zj@l@d@CPRj@CVHNRNl@P^^hBZr@h@f@xAh@\\MZ]pAyBb@mCf@iELy@DkAJgACeBFwAI{AAwAEm@@aBDgAAe@BOCYZqAd@yCEsCOwEKs@YqAYaA[q@YcAOWKa@QCQ]WGIOg@Mg@?aAHIRWRo@rBKTSRCHI|CI`AHjKEvAM|BY`CKf@@XKfAa@rB[x@UTCRGHe@b@WJU\\?PGRALg@dAEr@KTAT@Ht@`BZ`@FRPFNPJ\\JNZFVUVPH?ZOXFNZT`A?TEB@f@DHZRj@bA`@h@n@\\v@TLKP]`@[\\m@TsAL]FU@Y\\{Bh@oEFiAJi@A_AD_AKeBWyC@s@HoBF[Be@Nk@Lw@Ru@Jy@HkB]mIf@_B@SPu@@]J]h@qARw@h@aARGfALfD?lBMrADdAIjD@v@Gx@\\VDV[TGz@Ez@Sh@EbAD`AKx@JdAQ\\Jl@B~@?jACXD|@GTD|@AHFGpABx@AhAZA\\OHNRG`@L^O^CNMb@@H]^Dn@O\\QZGt@g@XGZ?bAc@TAPMl@CLITd@N?BEH[R]\\FFGFe@d@{@?ILWn@{@Zq@FSA]LSDUHOPo@NW@a@Ku@FaAAO?GQIGsALmAT}@x@cBDw@PiA@YCM?KEIY?Yi@SOGY@a@F[@YH_@DGNoADOHeAN[D]ZUTi@Bm@JOPEBo@BGTY@GHE", "average_heartrate": null, "average_speed": 2.523, "streak": 1}, {"run_id": 12665023188, "name": "15.10.2024", "distance": 7431.6, "moving_time": "0:51:03", "type": "Run", "start_date": "2024-10-15 13:37:20+00:00", "start_date_local": "2024-10-15 15:37:20", "location_country": "Germany", "summary_polyline": "_g`~Hmbf_AINM?G\\UVIEKKQBWp@Uz@QPICK\\]\\INQn@G@CJBTAVDdAKr@H\\@RHNb@h@LXd@b@XLFH?x@Ib@IXIJQNSf@_@`@QZQj@Ih@A^AtAFVZf@J^@NCx@Gx@AFIFALSPKNCJBFXBLJ?LM\\?FKFGTILQHa@B?FFZCTe@lAGb@KTMPUFUPQd@?J?CGEa@MO_AGW]gCCGGAYPIL{@bAQHQR[TECI\\KLo@Ai@Ju@@IAGMGCM@UPKFe@?MEYD]IY@O@?DCCy@JIAGB]XG@k@QUUIDCFAJMNQBMQQCCFCTEHG?k@WO?MG_@J]TGCKBGCSD[OIKIA_@a@_A@KHML]PKEEOCCUKUCMBg@Gq@?IDW@iAYOAUFWPQ@EDa@Aw@IWLMBEAACi@?OFIJMAIGcA@KEQBGCMBOLGB[FECOUGBEFE@UGg@HW?EEADGAKKa@KWDGJKE_@FMAu@QQ?UDo@ASBBBC@KASIe@NSBWKIB?@M@OOOEMDUAQGQCY@QCMBSGo@Eq@@SNg@LQTCLIPOf@I`A?X@G@??Q?HEEABEZ@pCBhAEf@Cx@DrDH`CM~BOnBIr@KjBUjACZMf@OfAc@`B_Av@e@N]`@YhA]`AFjBPd@h@b@PJBDXN\\j@Rj@HFTCRULGTC\\ML?DHHv@HTRx@JPNdAFJHDDJ`@h@d@Xt@V?EPHHANSHEf@_AV]HEPm@XkB`@eAd@aCBA?CN[@KRYDODq@Im@RwANwC?]Gk@GwAQsAEU@cAEcADaBHi@VcABoAM}C?w@GeA?_AFk@A{@X{Bv@yBd@o@`@{@FGJCd@LXCbAHn@?XE\\Bf@Cf@Dt@CPEXAZBXFLEd@ARBHHJ@HFFANOt@M~@@VCf@HLF^?BMFEDULGFAb@b@H@F?jA[ZAHBTENHH?ZGTBTARHL?VKrAGHDJ?XJj@K\\FRKLHTBZ?XG`@LNLVEh@?~AO|@Cn@BREV?REJ@RJJCVFRM`@]f@WXUv@a@\\IXQ~@}@HCLDLp@RfCP~@JLXx@FBPALGJQNk@b@_CJ[n@oA\\i@f@eAHYP@A[FG@WCoADi@A[Bw@AIOSEa@LY@_ADu@BMLUBFRiAR_BHcACe@GSE_@O_@E_@GACGAMAk@b@cAE_@AuBH_ATi@DULSDDDAJCJIL_@@O?[DS", "average_heartrate": null, "average_speed": 2.426, "streak": 1}, {"run_id": 12678059554, "name": "17.10.2024", "distance": 6273.5, "moving_time": "0:39:16", "type": "Run", "start_date": "2024-10-17 14:21:22+00:00", "start_date_local": "2024-10-17 16:21:22", "location_country": "Germany", "summary_polyline": "{j`~Hiee_AY^Q@GFWn@Kr@IlBF^PP@PETKVDHB^MbAH\\AJO^MHK?ACDC?JKZMVa@fAc@p@IZa@bAUR[PST_AmCEGICGg@CMAOCCc@L[DKDKLK@CBIIEF?NCFe@FGHSF_@D[TOVo@V_@HuAHOHc@BS?a@EWAODa@@a@JS?SIi@@i@KG?ODg@MKBYCc@IWKOA_@LSEW@KBIFUFED]FYJ_@EK@OJ_@GYIYHg@Bi@@OGOAOBY?_@CYRIIGAyAAg@@DHg@C[@KIE?MBIAGFo@CQHK?e@Gw@Jc@?SHW?MIIAQ@GCMFSGK@GAUQ?Ca@JYM[AmAJMEG?GB_@?GBE?MDm@@[SM?}@LcBOq@CU@WAu@IU?GGKCQBm@N[?EBKTKJc@fBM~B@fCItAHzDBfDGbBO~BGd@Y~AMrBMv@WtAM^e@bACJIB[v@E@IP[^i@tAIh@AlABLTl@T^RZp@r@LZNJHBFANCjAMTJv@vAHx@XpAb@|@pAz@TDJ?XIFIx@iAr@wBH{A^aAp@cGLuFEuAIcAI{BTwFJm@HELa@Do@B_ACiBGaBGmDL_A`@aABUAc@Fa@DIPQHEJ?LQr@uALQTUPa@NCHGb@@TEfA?RG|@FNAX?l@CHCzBHl@C\\LH?j@G\\?ZKPAXBLAX@\\HDCl@KZMd@Cl@ALD\\CfAFH?LE^D\\Gh@Bt@c@NA\\TTJNGRBVEf@@LC|@HdAAf@JX?\\Cl@CPCR@n@ALEh@Db@Cx@@RARDXANCDGRIRSdAm@r@m@TMLMh@YPUFJPdB\\xAHn@@AAA@@?CDDACJCZ?j@[\\e@", "average_heartrate": null, "average_speed": 2.663, "streak": 1}, {"run_id": 12739483768, "name": "20.10.2024", "distance": 7652.0, "moving_time": "0:47:50", "type": "Run", "start_date": "2024-10-20 12:46:00+00:00", "start_date_local": "2024-10-20 14:46:00", "location_country": "Germany", "summary_polyline": "yj`~Hk~d_As@rA@JnA}@mCtE\\kDINGCAG}@GAKq@VGFMb@\\?`BIPBFBBFICFFBFCxCMDE?MO_@Qc@DUPM`@OXMn@Ab@@h@C`BM^KbAo@D[VKUCONQ@KAICGa@MKIEIWu@BEEO?SF_@E?CGEBMf@ILQDSKSACJQRUGU?GD?CECAEi@AYBOLOBQROFCd@CFMFO@QDCGEEGAGKIBKHs@NSDWCa@HQAQGc@DIAaAI_@MKH_@@MPQ@OGAMMEaAOS?MI[CgATM@?AKCAJBD@EVb@w@g@w@k@OG_@UI?UFYA_@FKJK`@CDi@f@UJi@DiBAuAHqAA_@DQEoBBMEq@CcEFw@Ei@?{@AM@u@@g@HyA?u@H{@KKCOIKCQBa@CQBCCI@u@BMASGU@{AQI?ULMPMj@Ox@Ch@@r@CxBB|@KpABdAFr@BvB?zADl@Cr@Mp@Cj@U~BKxA?`@Gl@SnAOh@UdAINMh@OV]\\WF_@Z_@z@o@t@A^BbANTVn@\\b@XPZZl@bARJR@LPP@BBHRF?NID?HFJPb@dAV`AN`@f@v@r@`@NLJ@NFFAHENQb@[P[Hk@`@gAn@cCR{@Z_AVgBHSVoAHQ\\oAFm@Nu@@cBGWQmASk@LoACUIW?i@Bo@COBYEi@FkA@g@BQFiA@kAEo@?q@G_A?gALy@OeBJc@Dk@VcAVq@P[T_ALUDC`A_@f@?PE\\HVLH@dACj@Ef@DTA~D@d@G`@HVEd@Dn@GV@TAPGVCPM`AIx@D^Fd@@d@E^D^GVIb@GR@^HR?^F^APEn@BVAn@@`@KpAFd@AB?LPD?NGLAh@AT@dACnA@fAQRBJAx@Y\\Uf@UrA}@v@[NIPWVOJTb@xBtBp@A@?ATB?FB?`@w@RaAXe@JKPU?OFOTU^g@RQDM?[Le@?QHQCM?IRgAEm@Hg@@c@EYg@sAIe@Ce@B]Vi@Bi@ZoBH]BYCUq@]KOAq@Ik@?]A[@e@NuAP{@XgBLSHa@f@w@BKDi@", "average_heartrate": null, "average_speed": 2.666, "streak": 1}, {"run_id": 12739751233, "name": "25.10.2024", "distance": 7253.6, "moving_time": "0:53:51", "type": "Run", "start_date": "2024-10-25 08:42:29+00:00", "start_date_local": "2024-10-25 10:42:29", "location_country": "Germany", "summary_polyline": "eg`~H}bf_A[`@Mh@KJIRKlAENIFMPMXGXOz@Cl@E\\On@M`@EXE~@B`@LTZ\\\\PNNBZCTCHGHIBINGREh@Op@IHODQZER?^Kf@?XG`A@\\HPPNDHE|BIf@Bp@HV?TWz@?LKPE`@IJCPIFSf@ACE@IVGX[VGLOJSVOFY?IFST?PCHCGILCHEAEGMi@CYQ}@S_AIi@BWKEKM]V]NYTQDq@t@]Ru@j@e@RUDYIYBg@CsA?GAEEOFqAF]F}@AYFa@?_AG[Is@KqADOAi@R_@Fc@C_@?g@Js@F_@E_@A_@Ba@Cg@DMCW@g@B]CDA_@BYJI?s@K{@Ci@J[CiADqCAkAFu@?I@SAWGu@?UFy@BY?a@MWAQFs@Aw@D[M]IQFMCOAWF]CKEcAO}AAaAPQLKNIXSTM`@E^CbBEd@B`CG^ATJxBFxBBZCxABb@AXIj@QpCWlBOp@GR[dDM^ILSt@OZKNETq@j@MRKH_@r@Yr@Md@Cd@H^t@tAb@f@VLPPVX^h@b@E@DRGJ@XEJDNLDDLr@N\\R|@j@nAZ\\`Av@ZJ@CN?JE|@iAJc@D@Ng@Rw@JI@IHu@Lk@DcANaAFUCsBTq@Fk@DyBIiBFaAG}@FkA?eDBw@He@JWF[Tq@Lw@Bc@AaAKeASgE?k@HoAT_AVo@Lk@LMJg@Xo@PMb@mA\\U`@BVARFJ@FEDCJ@b@GL@FCL?JDLEt@BFBvAGn@BTDXIZBf@IR@JMPAVHNAJCBFN?JB`@@^A^UZWHAH@LFRTb@Rl@C\\GRA^FZNf@KL?LCNAFCHIJALHLBf@MP@VEj@DNCZDb@O^AVMFAPD\\RXCP@VFf@E\\BRCPBFDKdC?v@DFZJP@RL^FRAXOr@El@e@`@Sv@KNDXUT@JCJGNOd@SNAFB`@AhA[P@HEDEHJBHHBP[HGl@ADEFAXYHOJ[AW@IDMp@eAZsANKVcADKRIFMFCCQFaA?g@DcAAc@IMAMFaA?MGg@DqAF_AVOZ{@Pu@LuAASGOk@s@Wk@@_@Fs@l@{BRcABa@@a@BUV_@l@eAB[^eA", "average_heartrate": null, "average_speed": 2.245, "streak": 1}, {"run_id": 12759226957, "name": "27.10.2024", "distance": 2405.6, "moving_time": "0:19:35", "type": "Run", "start_date": "2024-10-27 11:16:58+00:00", "start_date_local": "2024-10-27 12:16:58", "location_country": "Germany", "summary_polyline": "sf`~Hicf_AONUf@K`@OL?FId@_@j@_@zAOdAK`BYjBG~@@FJPPPBHFFH@HHDLAl@BXC^WvAQVANWt@Ub@Ut@EXDbAPb@JHF?DIFAt@EVVd@DDALL\\HVAJ@bAOJ@HFJ?HSCYFMTLZVD@DCDHJDLBXALFBCBMJIBDEDDJD?JHL@XTNRJRNr@FHCBDXf@x@HDPPd@RXZFNB@@C?HEIG\\ABAAAf@m@bFON?J?z@DBJCJHPCV\\Q[GcAISQYYWYk@CIBWLGTk@HEH@@C?uAm@fAKMGOE_@Ao@By@E]Wg@Ok@{@kBOk@U_@Iu@I_@GAOi@EWDQDe@Tw@DmAEm@Om@@eAWaBYs@]UMQ[s@GCKU]_@Ww@IQa@W]_@I[Q_@I[?SBg@DORg@FINK", "average_heartrate": null, "average_speed": 2.047, "streak": 1}, {"run_id": 12812251102, "name": "03.11.2024", "distance": 7428.0, "moving_time": "0:48:44", "type": "Run", "start_date": "2024-11-03 11:05:48+00:00", "start_date_local": "2024-11-03 12:05:48", "location_country": "Germany", "summary_polyline": "wf`~Hibf_AMNCXEJ{@~@MBIHCNEd@GTg@b@Q\\]XQ\\m@x@s@p@Ul@Wh@AR@r@M|@@NHP?LS~@_@|DG`A@z@CTK`@CN@PFXJTRD^@|AEb@C^@FFF\\?^Gl@EDKBARA\\Hf@AJGTHNOHmAxAKZALSTS`@Gp@M\\SZEBO@EDUZCNC@EKABCAIW[[_@SGQM_AEkAGMAI]`@g@T[ZKBc@Rs@j@MBQHMJMT[Cc@BOCWDSA[@}@E[Bu@I]?a@Fm@@g@JWCc@BIBi@Ca@@MB_ACa@@]COH_@BCDSGO@]Ia@@QCo@DwAG}BJy@C]G_@Jk@DgAAg@D_@I]CWHE?c@E}@BUEO@aBHq@@KBSOm@BKCMDCCWCs@@IFa@Bq@IIDMCk@BUDQCm@CY?IB]E_@KQCq@?i@GKBIAI@GCe@I[Bk@HIFSFSPW^M\\?r@E`A@|@A`B@v@API`@AVF|@DzA?f@HpBAV@^CBAZ?\\Cb@@x@Mp@IL?d@EHApAW|@KvAMVKt@K\\Eb@Qx@EDg@Ro@j@a@z@IVg@v@I^ATDn@N`AHNf@b@PZJDNPDDJALDHTDVJNHFDABIHGHABKD@DGt@AH@@BVzAZp@TfAP`@LNNl@NNFBPCFD`@LH?XFHCX[\\U`@iAXo@Lk@^sCPwBJq@Do@VcA?IIi@Bu@Cc@@aBCsB@s@CM@_@E_BH_A@qAb@qAF[H_A@}BCcBMwD@e@ToBPo@Ji@Na@Xa@Rq@jAwB\\DPA?AHEPBNEh@HRCT@f@Ad@@b@CnABd@G\\Ad@Bv@GN@PDJ?TBXM^BdAEX@NCb@Qj@J^DJET@jACf@?TFh@Gb@A\\Kf@NJ?NE`@?XEx@?NERA~@BVEHBTBb@Ah@DT?v@DZE|@?XCr@?^B\\AREh@?JAr@YHE@GHCL@FAVOFIB@FGVONOb@QHBLQd@Mn@g@FBZ|@P~@HpALn@PMZEdAkAd@}@HYZ_@J[f@w@LYHOPIBIBw@I}BAgBIg@A[Mi@?}@Hm@Ja@b@w@VSJSLw@JgBKo@EKMI_@iAKk@AWBKDAHKB_AR{@\\kBh@_AVaAFm@DITSXm@", "average_heartrate": null, "average_speed": 2.54, "streak": 1}, {"run_id": 12838400927, "name": "07.11.2024", "distance": 6863.1, "moving_time": "0:56:59", "type": "Run", "start_date": "2024-11-06 16:16:50+00:00", "start_date_local": "2024-11-06 17:16:50", "location_country": "Germany", "summary_polyline": "mt`~Hskd_AANIZACFE@HS`@AR?BFAEHDDF\\@]AAC@OHCCAGVQBF__@]SCKNa@TECAB[?SEW?SMG?q@UK?WIe@HCGc@OGBCDKL_@Kc@Fa@@SES@WCWFy@Ma@MG?KPIAKDUAk@HMAGDu@QIBQJKBU?q@Ai@D_@As@@_@AO@GDe@CYNGAGGGCe@EMEO@GFK@QDe@KS@a@JY?ODo@IBBMKI@CHa@CO@ABKQ?GOJCFWIMBAFI?KHE?]KEEK?CKYIO@OBI?AIE?@CCAWHEAAEIDECg@@QAQBI?GG@IOFG@KLUAMHIAEBCLQZKd@GLKzACrCAV?d@Kt@Al@Dr@F~DDp@BtAEDANM`CM`AIz@SnDSbA[`AQ~@Sp@UNa@HSHKPWx@Q\\I^SNEFARA|@Hb@n@dA^Nx@r@JNBJP\\F@F?NE`@BPST@HCFHHd@HZHNADBTTn@D`@HX?VCr@DT?^UdCSn@EDI?QLK^CBCAG\\@N^CNKX]FEZCJOb@Ql@CVKJMREV@VD~@YZU?I`@o@Pa@HOLIHBP@v@`@`@LJ?ZFX?VIH@pAYBEJCn@a@XKx@iAPK\\]Za@ZSV[VUHSX_@p@i@j@q@L@HCZSJOTMj@c@f@wANWzAqBVWRIP[DB@APg@LUHCl@_@ZOLMJADIXKn@ADEVELBNNLXB@DZh@vBPb@RNFNDDNb@Lt@BFB?XKFAbA[`@YVGf@CFFX?JBj@MPKbAGTUNEb@GPG`@EJEh@q@`@Ob@ETHJ?TGhAP`@JHCNKRY^YH@HC|@Gz@Bz@MRSf@Uf@m@TOFAROJCRQJC?K@JPTfB}AQEQQCKBSCEICCC@c@Ii@BYAUOe@Uc@]aAA@Ea@YoA[}@Iy@@c@GQM_BHk@?WG{@QeAM_BG[Ge@?o@GqA@]We@CMLCBi@@IB@CBAKLOJ?NFH?^ER?FEp@m@Ra@^UPST]FSP[BIGk@?o@J_DC}@Ms@?SF[Mm@?cALeAJGXELUHULaAJc@Be@Hk@Q_BKU[a@Sa@AI@g@BMRg@HYFe@R{@PwA\\i@T{@F?HCCIBW", "average_heartrate": null, "average_speed": 2.007, "streak": 1}, {"run_id": 12858078940, "name": "09.11.2024", "distance": 10339.3, "moving_time": "1:08:43", "type": "Run", "start_date": "2024-11-09 09:22:20+00:00", "start_date_local": "2024-11-09 10:22:20", "location_country": "Germany", "summary_polyline": "}g`~Hqaf_AKb@SNKXQHO|AI\\IJSxAWl@G`AUbAA\\Fh@l@rALBPPBTYlBc@`Aa@|AOzAIrATl@DVBx@EjBFz@GPKz@Of@MNY@[Na@ZYf@ETOf@[Tk@z@QpBFg@Ag@LCUGC[EIAw@IUBc@EGIsAQIYC}@NYNc@Je@Xu@Ns@f@Od@Yb@KDGPQGuDHgAQ{ATaBKy@H{C?}APcBM}@NqBEu@D{@Cs@He@UIFOCSLSE_AP}BQqEAiAMi@@e@Nk@Am@L{@KaBFaAG_@F{@YsCCcBMmANa@z@If@IpCEVAx@BnAKtAPpEBxDUlDM|@MpBBh@GJO`AMd@g@~Dg@JGNs@Tw@|@k@z@?x@G`@DHL@b@t@VFDVJNPp@d@f@f@x@h@ARLECV?j@Th@v@Lj@HrAAzCGnA@LH?^]Pc@LMv@Ol@i@h@u@Vk@lAcBJc@B_@Lu@VaCFU@OTaA`@w@BmAb@qCJU?KCWJ_@@_@a@{A?e@Bk@Iw@@kAEoADI@o@FY@u@I{@E}EMmBEkB]kBi@aBSy@Q[Wy@OuAGUa@MuCKkADWLs@pBGfCFrCGhA@|APzFI|Ba@zEgAbHYjASf@cAt@Uh@c@p@[x@Cd@Bh@HLH^T\\L^Lf@Bd@\\b@f@TTKZDLTHDr@INZPLZHERPj@\\~BA^Y~BBDHEDLVB?\\FRB@`@Sn@}@j@Op@q@Vk@b@sA\\i@Ja@?WHo@ZcBFuAf@aCPmAFOGc@LuAFeAG_A@YC]Be@WcCE}CB[Pe@?WVyAFw@SwH@qABWHSBULa@Fi@f@yAl@_ATcAPWD]j@_@t@GjBLHIpBBzEMf@B\\LtAS~@B~AEHKAEt@Kd@Fd@JrCGTFlBg@v@LzABfBGz@HTExDHtBQXFLNn@?fBg@Z?VWh@O^_@\\OX]N]@PJVCNHfAd@vAB\\dAe@b@Gb@aALIX?FOHIT{ARo@\\}@@{@Tm@Fc@BaEXJzAD`AVlAGh@JHELc@h@Hl@^f@?FKQkDDc@PIFMIy@FoAAWKi@Uo@VaA@UQm@o@kASKUWe@u@a@oCGg@GIKFWt@Yd@Qd@UVe@bAQKOBSTc@~A?`AEBOYEeAG]JGLSJ]Hk@HkBF]b@kANMFQ`@wANW?SJ[LU", "average_heartrate": null, "average_speed": 2.508, "streak": 1}, {"run_id": 12882243487, "name": "12.11.2024", "distance": 7542.8, "moving_time": "0:43:19", "type": "Run", "start_date": "2024-11-12 10:07:33+00:00", "start_date_local": "2024-11-12 11:07:33", "location_country": "Germany", "summary_polyline": "}b`~Hsye_ABNVj@Hl@eCKgCSg@Ae@tA@^_@^ELCZ@^AJA@DBa@Fz@VBPGb@Mb@C^Ov@Il@@RAHPB@@Uf@Sz@MlA?RDf@HXE|@BXBDBN?tARn@@\\Jl@BA?JIVE@AEC?AAAt@CJ[^OVIl@Qp@{@|@OFWBOJODGPDCKNAGIDIMMEEi@K?IIWc@Kg@EkAOY_@v@WNQXO?WHI@YHa@\\QJy@^QBUCIEqALeAE{@Bk@?UBm@?_@Fw@MUB[CSBmBIeABm@TK@y@CqBFkEEg@DU?_ADaB@c@Da@Ee@@MASBu@Ew@?k@DsB?WBYCs@?g@DgACQEKF]@UCi@B[E}A@k@Ai@OWDc@CM@s@KeBKQFU?MJ_@`@[p@Qp@Ed@A~CDrAGnADxDJ~B?bAMvCQ|A]dEMv@Qt@o@xBW\\u@\\q@n@{@`CC\\DNDrAF\\LVX\\~@t@T^^`@`@LLI|@UF@LHNRFVDV?PB^Rt@^`Af@n@PFl@^^@`@Sx@iAZcAj@sCJm@NyAHSD{@Jc@Jo@E[H_AFwBGiB@eAIs@GcB?i@DyAHiAJc@HYJOF[ReB?q@Cm@AqAMkDBqAj@iDNg@d@gA\\a@N]h@y@\\MZCx@?d@F|@KP@TAbAANE|AFx@CNB\\CXDl@BNCh@?|@IfACb@D~@En@?hASH@PFb@Eh@BV?RGZDXANC\\BT?PBP?XEVB~@Kx@HZ?`@EN@^LR@fAKlBA`@CJ@r@AHCnAJXWXIr@g@XCNOVMb@c@`@Wn@m@HGBF@ZLfAVhBPj@FDLKD@RCl@WVe@Lk@@MDIRDTT]TPAPDNw@b@iDl@aB?QD]@]EIGe@A}@De@DKVKd@MNKf@RPP\\H^CJ?PFVCNDLEl@FDG?YDKLDTXTPPDR@HAPKR]A[c@aBAODe@\\wABmAAw@E_@Sy@U_B", "average_heartrate": null, "average_speed": 2.902, "streak": 1}, {"run_id": 12898030209, "name": "14.11.2024", "distance": 6885.5, "moving_time": "0:45:31", "type": "Run", "start_date": "2024-11-14 09:59:38+00:00", "start_date_local": "2024-11-14 10:59:38", "location_country": "Germany", "summary_polyline": "af`~Hscf_A]b@SJGHIVEFMXGZIJk@xAQXQ|@Sr@CdBG\\C@GOQg@UYQIWLWTYj@Gf@K`@@x@LnB@x@AXQ|@g@dAMZIb@Mt@AbAKh@ABCACDcAp@Un@WNCd@DRQ`@aAx@k@Ry@NWFIHKPe@JYZM^Ij@KRIXINIb@Ev@UZoAFKEQ?UGe@?OC_@@[FYAu@@_@EM@UEYBk@AUFwALaA@YEU?u@Be@Au@F}BAc@@c@Ao@@KA[BSCiBDa@Eq@NMAS@c@A[@g@Ey@?U@OHK@WGa@C]@QCi@AMB_@Ao@Bc@AgA@e@BU?G@i@Ea@@m@Em@BcAKeAQw@Bu@GcADg@Jw@rAK^Iz@BlBH|BIvA@hCDpBB`Du@~ISrAOl@WrBK^Uf@G@KAE@cAh@Qd@KNMb@OZK`@MNCf@?HJTLv@T^DLRTHB`@j@\\NFFPb@LFNATG|@ON@DDJt@Xh@Hj@j@lBX`@b@\\p@\\HCPFR?FCXa@HGPYDYJMFM^aAFm@J]Jw@LwA@}@\\cAHg@RmBAi@DaA@u@UgD@a@Gk@A_@Bm@LeBFgBFYTs@PaBIcB@kAGwAE}ABiAD_@Pg@JuAJg@v@mBTc@JEXg@@SHMTIVEJBR?`@DZ?J@RGPAPFr@DhAGr@?NBf@GbA?f@GLD`@?TEPANFR?LEH@NCF@`AAl@@WCCCn@D^AVEZ?VFfAK^BVE`@@JDFAb@Wh@Rd@?^Dr@EZDrAQBB^BPHHGTBVAPBb@P`@GzACh@GV@n@?VGX?\\GJMFWEa@AkA\\i@VOp@u@d@OTOLKHUNQl@c@d@YLOF?HFBOLDNSDCDTVLX?\\ENEPK^e@BWCIQa@QOFe@?mAQmAVgAV{@B_@A}@Ge@Aq@Mo@EMAQVa@bA_CbBsGRaAPg@^{AJSZSHALF", "average_heartrate": null, "average_speed": 2.521, "streak": 1}, {"run_id": 12911948127, "name": "16.11.2024", "distance": 8638.7, "moving_time": "0:56:59", "type": "Run", "start_date": "2024-11-16 08:49:09+00:00", "start_date_local": "2024-11-16 09:49:09", "location_country": "Germany", "summary_polyline": "{g`~H{af_AMFGAKOASB]IKA@G`@EHaAF_@Ry@vAi@lAKJYj@a@hBc@z@I@@JG?ADYIEKCUGaA@QHS?UCKKKB]CWe@eAQg@_@u@Ce@Sa@EWGG]VQ@QECIMKGFBJEDGBUCONGR@FCf@GZKfAKh@GPCXCPBt@H\\JRBVFfBCbALj@B\\Lh@V|Ah@tEN`AHXBh@H|@B?H\\NtAHPGA?d@Fp@AE@BE?EI@LINs@LS?uBv@KJU^s@`@KJMZOLKZET@b@STBDALEXO@ERMJoETaAA]JgAO_A@aAOoABi@Vq@GQFq@Ei@Jc@@qAEi@Ju@BaBC[GoANyBUULm@?k@HkBEu@FUCa@Hc@OIAADOE_AFyAEaAN}@QwBF_@KwCGk@D_AO{@DSJMLQb@SfAKfBCtCG`BJbCFl@?|ADhA?x@MhBGj@I\\IpAI`@S^@LARMf@KlA[vBWt@QV]XMRc@^k@t@_@jAQ~@Lv@XCDDXl@LJj@fAPXRRHR^LHJDN^St@Vp@AC`@d@p@f@|@bBzATPJ@DJRFFCRa@`A{ALqAHk@Ba@Hc@@_AJSH_@N_BFIL[H}@Aw@CMDiAGqDD}BAy@B{AIsAFi@f@oCB]C}BKu@Ao@M_BEsBSeAYs@c@uAa@w@w@cAc@c@c@OyASw@YM?e@h@KTS|@Gr@C~@@`BI~ANjFBvCIp@?tAKtAk@`FK\\_@pCi@hB]^o@b@g@x@KVOPSl@E~@BLh@nAXXZr@d@f@NFT^RL?FBBj@OTOb@L`@r@Pj@R`Aj@zAb@Th@l@XNRDTGXYXq@n@{@VYLST}@DY?y@Dg@P}@RcBNm@DiAA_AOuCAiAFeBGs@?}CC{@Da@v@wC@eAIeB~hAmqABRR?NR^FFPLMN?BB@b@CTBx@Iz@DLNrBTx@RLLPDP@VLt@HNN@Pb@BADSj@}@XSr@@^Nz@v@BXAp@BXHRLRt@d@Cn@_@lCIVi@fAYr@Ib@E`@@f@FTVb@\\?ZI`@Bj@VXD^E\\Ht@Cn@HLEB_@HKF@\\d@b@RTBRIBOCo@@k@Gc@AUXaDBKDG?SHo@?_@I{@WmAEg@Mo@]oAWm@Qs@KeBGUq@iAa@Wq@y@]WMQEOKKBQVE", "average_heartrate": null, "average_speed": 2.527, "streak": 1}]